{
  "season": "2019-04",
  "series": [
    {
      "id": 3006,
      "title": "Kouya no Kotobuki Hikoutai",
      "image": "https://i.imgur.com/rlpTZYQ.jpg",
      "malId": 38301,
      "rating": 6,
      "totalEpisodes": 12,
      "season": {
        "year": 2019,
        "season": "Winter"
      }
    },
    {
      "id": 2985,
      "title": "Mob Psycho 100 II",
      "image": "https://i.imgur.com/aFhslCY.jpg",
      "malId": 37510,
      "rating": 7,
      "totalEpisodes": 13,
      "season": {
        "year": 2019,
        "season": "Winter"
      }
    },
    {
      "id": 3012,
      "title": "Kemono Friends 2",
      "image": "https://i.imgur.com/VYHxfox.jpg",
      "malId": 35313,
      "rating": 5,
      "totalEpisodes": 12,
      "season": {
        "year": 2019,
        "season": "Winter"
      }
    },
    {
      "id": 3033,
      "title": "Piano no Mori (TV) 2nd Season",
      "image": "https://i.imgur.com/s2SwXMv.jpg",
      "malId": 37975,
      "rating": 4,
      "totalEpisodes": 12,
      "season": {
        "year": 2019,
        "season": "Winter"
      }
    },
    {
      "id": 1929,
      "title": "Black Clover (TV)",
      "image": "https://i.imgur.com/a8CF1mA.jpg",
      "malId": 34572,
      "rating": 0,
      "totalEpisodes": 0,
      "season": {
        "year": 2017,
        "season": "Fall"
      }
    },
    {
      "id": 3087,
      "title": "Diamond no Ace: Act II",
      "image": "https://i.imgur.com/8pOLWdG.jpg",
      "malId": 38731,
      "rating": 0,
      "totalEpisodes": 52,
      "season": {
        "year": 2019,
        "season": "Spring"
      }
    },
    {
      "id": 2368,
      "title": "Layton Mystery Tanteisha: Katri no Nazotoki File",
      "image": "https://i.imgur.com/UtSA4tw.jpg",
      "malId": 37023,
      "rating": 5,
      "totalEpisodes": 50,
      "season": {
        "year": 2018,
        "season": "Spring"
      }
    },
    {
      "id": 3091,
      "title": "Kono Yo no Hate de Koi wo Utau Shoujo YU-NO",
      "image": "https://i.imgur.com/dHKKHXU.jpg",
      "malId": 34620,
      "rating": 5,
      "totalEpisodes": 26,
      "season": {
        "year": 2019,
        "season": "Spring"
      }
    },
    {
      "id": 3008,
      "title": "Tate no Yuusha no Nariagari",
      "image": "https://i.imgur.com/i5XeKZy.jpg",
      "malId": 35790,
      "rating": 5,
      "totalEpisodes": 25,
      "season": {
        "year": 2019,
        "season": "Winter"
      }
    },
    {
      "id": 2322,
      "title": "Captain Tsubasa (2018)",
      "image": "https://i.imgur.com/SJ5VStv.jpg",
      "malId": 36934,
      "rating": 4,
      "totalEpisodes": 52,
      "season": {
        "year": 2018,
        "season": "Spring"
      }
    },
    {
      "id": 3040,
      "title": "Fight League: Gear Gadget Generators",
      "image": "https://i.imgur.com/FdFDTZm.jpg",
      "malId": 38719,
      "rating": 3,
      "totalEpisodes": 26,
      "season": {
        "year": 2019,
        "season": "Winter"
      }
    },
    {
      "id": 2821,
      "title": "Karakuri Circus",
      "image": "https://i.imgur.com/A7Cu4F7.jpg",
      "malId": 37447,
      "rating": 6,
      "totalEpisodes": 36,
      "season": {
        "year": 2018,
        "season": "Fall"
      }
    },
    {
      "id": 2809,
      "title": "Toaru Majutsu no Index III",
      "image": "https://i.imgur.com/Z9rZt5R.jpg",
      "malId": 36432,
      "rating": 4,
      "totalEpisodes": 26,
      "season": {
        "year": 2018,
        "season": "Fall"
      }
    },
    {
      "id": 2414,
      "title": "Cardfight!! Vanguard (2018)",
      "image": "https://i.imgur.com/YlDGLCX.jpg",
      "malId": 37476,
      "rating": 5,
      "totalEpisodes": 52,
      "season": {
        "year": 2018,
        "season": "Spring"
      }
    },
    {
      "id": 3102,
      "title": "Fruits Basket (2019)",
      "image": "https://i.imgur.com/5XuppGv.jpg",
      "malId": 38680,
      "rating": 5,
      "totalEpisodes": 25,
      "season": {
        "year": 2019,
        "season": "Spring"
      }
    },
    {
      "id": 3103,
      "title": "Senryuu Shoujo",
      "image": "https://i.imgur.com/xb3nxSW.jpg",
      "malId": 38787,
      "rating": 4,
      "totalEpisodes": 12,
      "season": {
        "year": 2019,
        "season": "Spring"
      }
    },
    {
      "id": 3104,
      "title": "Midara na Ao-chan wa Benkyou ga Dekinai",
      "image": "https://i.imgur.com/KYZgqOh.jpg",
      "malId": 38778,
      "rating": 6,
      "totalEpisodes": 12,
      "season": {
        "year": 2019,
        "season": "Spring"
      }
    },
    {
      "id": 3105,
      "title": "Hitoribocchi no Marumaru Seikatsu",
      "image": "https://i.imgur.com/QvpJInd.jpg",
      "malId": 37614,
      "rating": 7,
      "totalEpisodes": 12,
      "season": {
        "year": 2019,
        "season": "Spring"
      }
    },
    {
      "id": 2652,
      "title": "JoJo no Kimyou na Bouken: Ougon no Kaze",
      "image": "https://i.imgur.com/zaNflT2.jpg",
      "malId": 37991,
      "rating": 9,
      "totalEpisodes": 39,
      "season": {
        "year": 2018,
        "season": "Fall"
      }
    },
    {
      "id": 3010,
      "title": "Hulaing Babies",
      "image": "https://i.imgur.com/7jDMRbh.jpg",
      "malId": 34332,
      "rating": 2,
      "totalEpisodes": 12,
      "season": {
        "year": 2019,
        "season": "Winter"
      }
    },
    {
      "id": 122,
      "title": "Boruto: Naruto Next Generations",
      "image": "https://i.imgur.com/O5vYeDw.jpg",
      "malId": 34566,
      "rating": 0,
      "totalEpisodes": 0,
      "season": {
        "year": 2017,
        "season": "Spring"
      }
    },
    {
      "id": 2805,
      "title": "Fairy Tail: Final Series",
      "image": "https://i.imgur.com/1ogsfhX.jpg",
      "malId": 35972,
      "rating": 5,
      "totalEpisodes": 51,
      "season": {
        "year": 2018,
        "season": "Fall"
      }
    },
    {
      "id": 2306,
      "title": "Gegege no Kitarou (2018)",
      "image": "https://i.imgur.com/p0ftolA.jpg",
      "malId": 37140,
      "rating": 0,
      "totalEpisodes": 0,
      "season": {
        "year": 2018,
        "season": "Spring"
      }
    },
    {
      "id": 3106,
      "title": "Joshikausei",
      "image": "https://i.imgur.com/B9GPEfz.jpg",
      "malId": 38295,
      "rating": 3,
      "totalEpisodes": 12,
      "season": {
        "year": 2019,
        "season": "Spring"
      }
    },
    {
      "id": 3108,
      "title": "Choukadou Girl ⅙",
      "image": "https://i.imgur.com/pRJPFbb.jpg",
      "malId": 38226,
      "rating": 4,
      "totalEpisodes": 12,
      "season": {
        "year": 2019,
        "season": "Spring"
      }
    },
    {
      "id": 3112,
      "title": "Kono Oto Tomare!",
      "image": "https://i.imgur.com/fgu30d6.jpg",
      "malId": 38080,
      "rating": 5,
      "totalEpisodes": 13,
      "season": {
        "year": 2019,
        "season": "Spring"
      }
    },
    {
      "id": 3107,
      "title": "Mix: Meisei Story",
      "image": "https://i.imgur.com/Vcvy9RT.jpg",
      "malId": 38098,
      "rating": 4,
      "totalEpisodes": 24,
      "season": {
        "year": 2019,
        "season": "Spring"
      }
    },
    {
      "id": 3110,
      "title": "Nobunaga-sensei no Osanazuma",
      "image": "https://i.imgur.com/R7RvtEE.jpg",
      "malId": 38814,
      "rating": 4,
      "totalEpisodes": 12,
      "season": {
        "year": 2019,
        "season": "Spring"
      }
    },
    {
      "id": 3109,
      "title": "Bokutachi wa Benkyou ga Dekinai",
      "image": "https://i.imgur.com/ZhAIe2U.jpg",
      "malId": 38186,
      "rating": 5,
      "totalEpisodes": 13,
      "season": {
        "year": 2019,
        "season": "Spring"
      }
    },
    {
      "id": 3111,
      "title": "Kimetsu no Yaiba",
      "image": "https://i.imgur.com/wfLo5pf.jpg",
      "malId": 38000,
      "rating": 7,
      "totalEpisodes": 26,
      "season": {
        "year": 2019,
        "season": "Spring"
      }
    },
    {
      "id": 3113,
      "title": "Fairy Gone",
      "image": "https://i.imgur.com/d6aXWZt.jpg",
      "malId": 39063,
      "rating": 6,
      "totalEpisodes": 12,
      "season": {
        "year": 2019,
        "season": "Spring"
      }
    },
    {
      "id": 3116,
      "title": "Hachigatsu no Cinderella Nine",
      "image": "https://i.imgur.com/JNdMfAS.jpg",
      "malId": 38091,
      "rating": 4,
      "totalEpisodes": 12,
      "season": {
        "year": 2019,
        "season": "Spring"
      }
    },
    {
      "id": 3118,
      "title": "Mayonaka no Occult Koumuin",
      "image": "https://i.imgur.com/WnugAST.jpg",
      "malId": 37964,
      "rating": 5,
      "totalEpisodes": 12,
      "season": {
        "year": 2019,
        "season": "Spring"
      }
    },
    {
      "id": 3119,
      "title": "Shoumetsu Toshi",
      "image": "https://i.imgur.com/rWxMGfM.jpg",
      "malId": 37952,
      "rating": 3,
      "totalEpisodes": 12,
      "season": {
        "year": 2019,
        "season": "Spring"
      }
    },
    {
      "id": 3120,
      "title": "Nande Koko ni Sensei ga!?",
      "image": "https://i.imgur.com/IVNGtV2.jpg",
      "malId": 38397,
      "rating": 5,
      "totalEpisodes": 12,
      "season": {
        "year": 2019,
        "season": "Spring"
      }
    },
    {
      "id": 3117,
      "title": "Araiya-san!: Ore to Aitsu ga Onnayu de!?",
      "image": "https://i.imgur.com/G8TqCpb.jpg",
      "malId": 39337,
      "rating": 3,
      "totalEpisodes": 8,
      "season": {
        "year": 2019,
        "season": "Spring"
      }
    },
    {
      "id": 2986,
      "title": "Dororo",
      "image": "https://i.imgur.com/HzzNDoM.jpg",
      "malId": 37520,
      "rating": 8,
      "totalEpisodes": 24,
      "season": {
        "year": 2019,
        "season": "Winter"
      }
    },
    {
      "id": 3121,
      "title": "Namu Amida Butsu!: Rendai Utena",
      "image": "https://i.imgur.com/R6S0ZV0.jpg",
      "malId": 38150,
      "rating": 3,
      "totalEpisodes": 12,
      "season": {
        "year": 2019,
        "season": "Spring"
      }
    },
    {
      "id": 3122,
      "title": "RobiHachi",
      "image": "https://i.imgur.com/gc7PN3e.jpg",
      "malId": 38707,
      "rating": 4,
      "totalEpisodes": 12,
      "season": {
        "year": 2019,
        "season": "Spring"
      }
    },
    {
      "id": 3123,
      "title": "Yatogame-chan Kansatsu Nikki",
      "image": "https://i.imgur.com/aruZSoM.jpg",
      "malId": 37940,
      "rating": 3,
      "totalEpisodes": 12,
      "season": {
        "year": 2019,
        "season": "Spring"
      }
    },
    {
      "id": 3124,
      "title": "One Punch Man 2nd Season",
      "image": "https://i.imgur.com/ueW1ueY.jpg",
      "malId": 34134,
      "rating": 6,
      "totalEpisodes": 12,
      "season": {
        "year": 2019,
        "season": "Spring"
      }
    },
    {
      "id": 3125,
      "title": "Isekai Quartet",
      "image": "https://i.imgur.com/Dw7aYzV.jpg",
      "malId": 38472,
      "rating": 4,
      "totalEpisodes": 12,
      "season": {
        "year": 2019,
        "season": "Spring"
      }
    },
    {
      "id": 3126,
      "title": "Strike Witches: 501 Butai Hasshin Shimasu!",
      "image": "https://i.imgur.com/8QFqNUK.jpg",
      "malId": 38004,
      "rating": 3,
      "totalEpisodes": 12,
      "season": {
        "year": 2019,
        "season": "Spring"
      }
    },
    {
      "id": 3127,
      "title": "Sewayaki Kitsune no Senko-san",
      "image": "https://i.imgur.com/9Sls7DZ.jpg",
      "malId": 38759,
      "rating": 5,
      "totalEpisodes": 12,
      "season": {
        "year": 2019,
        "season": "Spring"
      }
    },
    {
      "id": 2806,
      "title": "Okoshiyasu, Chitose-chan",
      "image": "https://i.imgur.com/CuGZWQU.jpg",
      "malId": 38089,
      "rating": 3,
      "totalEpisodes": 24,
      "season": {
        "year": 2018,
        "season": "Fall"
      }
    },
    {
      "id": 3129,
      "title": "Kenja no Mago",
      "image": "https://i.imgur.com/exlEKB6.jpg",
      "malId": 36407,
      "rating": 6,
      "totalEpisodes": 12,
      "season": {
        "year": 2019,
        "season": "Spring"
      }
    },
    {
      "id": 3131,
      "title": "Carole & Tuesday",
      "image": "https://i.imgur.com/nrf2tSE.jpg",
      "malId": 37435,
      "rating": 5,
      "totalEpisodes": 24,
      "season": {
        "year": 2019,
        "season": "Spring"
      }
    },
    {
      "id": 3132,
      "title": "Gunjou no Magmel",
      "image": "https://i.imgur.com/jUQ6sqU.jpg",
      "malId": 37806,
      "rating": 6,
      "totalEpisodes": 13,
      "season": {
        "year": 2019,
        "season": "Spring"
      }
    },
    {
      "id": 3133,
      "title": "Sarazanmai",
      "image": "https://i.imgur.com/VdYhmYC.jpg",
      "malId": 37426,
      "rating": 4,
      "totalEpisodes": 11,
      "season": {
        "year": 2019,
        "season": "Spring"
      }
    },
    {
      "id": 3135,
      "title": "Bungou Stray Dogs 3rd Season",
      "image": "https://i.imgur.com/EKZclci.jpg",
      "malId": 38003,
      "rating": 6,
      "totalEpisodes": 12,
      "season": {
        "year": 2019,
        "season": "Spring"
      }
    },
    {
      "id": 3142,
      "title": "King of Prism: Shiny Seven Stars",
      "image": "https://i.imgur.com/e9GI7aA.jpg",
      "malId": 39699,
      "rating": 3,
      "totalEpisodes": 12,
      "season": {
        "year": 2019,
        "season": "Spring"
      }
    },
    {
      "id": 2515,
      "title": "Dragon Ball Heroes",
      "image": "https://i.imgur.com/ajG41Y3.jpg",
      "malId": 37885,
      "rating": 0,
      "totalEpisodes": 0,
      "season": {
        "year": 2018,
        "season": "Summer"
      }
    },
    {
      "id": 3014,
      "title": "Circlet Princess",
      "image": "https://i.imgur.com/lZNxMSN.jpg",
      "malId": 38157,
      "rating": 4,
      "totalEpisodes": 12,
      "season": {
        "year": 2019,
        "season": "Winter"
      }
    },
    {
      "id": 3185,
      "title": "Shingeki no Kyojin Season 3 Part 2",
      "image": "https://i.imgur.com/R95n8JR.jpg",
      "malId": 38524,
      "rating": 7,
      "totalEpisodes": 10,
      "season": {
        "year": 2019,
        "season": "Spring"
      }
    },
    {
      "id": 3216,
      "title": "Cardfight!! Vanguard: Zoku Koukousei-hen",
      "image": "https://i.imgur.com/zbaLdcE.jpg",
      "malId": 39244,
      "rating": 4,
      "totalEpisodes": 14,
      "season": {
        "year": 2019,
        "season": "Spring"
      }
    },
    {
      "id": 3212,
      "title": "Miru Tights",
      "image": "https://i.imgur.com/rzToxFj.jpg",
      "malId": 38935,
      "rating": 5,
      "totalEpisodes": 12,
      "season": {
        "year": 2019,
        "season": "Spring"
      }
    }
  ],
  "episodes": [
    {
      "id": 26269,
      "date": "2019-04-01 17:07:23.681 +00:00",
      "episode": 12,
      "rating": 6,
      "animeId": 3006
    },
    {
      "id": 25977,
      "date": "2019-04-01 18:12:17.735 +00:00",
      "episode": 13,
      "rating": 7,
      "animeId": 2985
    },
    {
      "id": 26336,
      "date": "2019-04-01 21:36:57.329 +00:00",
      "episode": 12,
      "rating": 5,
      "animeId": 3012
    },
    {
      "id": 26805,
      "date": "2019-04-02 15:57:22.121 +00:00",
      "episode": 9,
      "rating": 4,
      "animeId": 3033
    },
    {
      "id": 16108,
      "date": "2019-04-02 16:18:13.556 +00:00",
      "episode": 77,
      "rating": 5,
      "animeId": 1929
    },
    {
      "id": 27092,
      "date": "2019-04-02 18:01:07.632 +00:00",
      "episode": 1,
      "rating": 5,
      "animeId": 3087
    },
    {
      "id": 20357,
      "date": "2019-04-02 21:35:30.368 +00:00",
      "episode": 50,
      "rating": 6,
      "animeId": 2368
    },
    {
      "id": 27106,
      "date": "2019-04-03 18:03:16.587 +00:00",
      "episode": 1,
      "rating": 6,
      "animeId": 3091
    },
    {
      "id": 26294,
      "date": "2019-04-03 21:36:24.297 +00:00",
      "episode": 13,
      "rating": 6,
      "animeId": 3008
    },
    {
      "id": 19727,
      "date": "2019-04-04 15:57:01.858 +00:00",
      "episode": 51,
      "rating": 4,
      "animeId": 2322
    },
    {
      "id": 26860,
      "date": "2019-04-04 16:04:12.511 +00:00",
      "episode": 8,
      "rating": 3,
      "animeId": 3040
    },
    {
      "id": 24623,
      "date": "2019-04-04 21:41:59.271 +00:00",
      "episode": 24,
      "rating": 7,
      "animeId": 2821
    },
    {
      "id": 24457,
      "date": "2019-04-05 15:49:14.090 +00:00",
      "episode": 26,
      "rating": 4,
      "animeId": 2809
    },
    {
      "id": 20821,
      "date": "2019-04-06 15:55:06.017 +00:00",
      "episode": 48,
      "rating": 4,
      "animeId": 2414
    },
    {
      "id": 27126,
      "date": "2019-04-06 16:22:45.830 +00:00",
      "episode": 1,
      "rating": 6,
      "animeId": 3102
    },
    {
      "id": 27131,
      "date": "2019-04-06 16:35:10.580 +00:00",
      "episode": 1,
      "rating": 5,
      "animeId": 3103
    },
    {
      "id": 27136,
      "date": "2019-04-06 16:47:32.163 +00:00",
      "episode": 1,
      "rating": 6,
      "animeId": 3104
    },
    {
      "id": 27141,
      "date": "2019-04-06 17:10:51.423 +00:00",
      "episode": 1,
      "rating": 8,
      "animeId": 3105
    },
    {
      "id": 22704,
      "date": "2019-04-06 20:08:28.469 +00:00",
      "episode": 25,
      "rating": 8,
      "animeId": 2652
    },
    {
      "id": 26310,
      "date": "2019-04-07 08:14:54.213 +00:00",
      "episode": 10,
      "rating": 2,
      "animeId": 3010
    },
    {
      "id": 26311,
      "date": "2019-04-07 08:14:54.214 +00:00",
      "episode": 11,
      "rating": 2,
      "animeId": 3010
    },
    {
      "id": 26312,
      "date": "2019-04-07 08:14:54.215 +00:00",
      "episode": 12,
      "rating": 2,
      "animeId": 3010
    },
    {
      "id": 1537,
      "date": "2019-04-07 14:35:07.294 +00:00",
      "episode": 101,
      "rating": 5,
      "animeId": 122
    },
    {
      "id": 24389,
      "date": "2019-04-07 14:49:17.404 +00:00",
      "episode": 26,
      "rating": 5,
      "animeId": 2805
    },
    {
      "id": 19285,
      "date": "2019-04-07 15:06:24.993 +00:00",
      "episode": 50,
      "rating": 6,
      "animeId": 2306
    },
    {
      "id": 27146,
      "date": "2019-04-07 15:09:53.688 +00:00",
      "episode": 1,
      "rating": 4,
      "animeId": 3106
    },
    {
      "id": 27156,
      "date": "2019-04-07 15:21:21.175 +00:00",
      "episode": 1,
      "rating": 6,
      "animeId": 3108
    },
    {
      "id": 27176,
      "date": "2019-04-07 15:43:27.957 +00:00",
      "episode": 1,
      "rating": 6,
      "animeId": 3112
    },
    {
      "id": 27151,
      "date": "2019-04-07 16:08:00.737 +00:00",
      "episode": 1,
      "rating": 4,
      "animeId": 3107
    },
    {
      "id": 27166,
      "date": "2019-04-07 16:15:43.272 +00:00",
      "episode": 1,
      "rating": 4,
      "animeId": 3110
    },
    {
      "id": 27161,
      "date": "2019-04-07 17:12:32.703 +00:00",
      "episode": 1,
      "rating": 5,
      "animeId": 3109
    },
    {
      "id": 27171,
      "date": "2019-04-07 17:35:50.236 +00:00",
      "episode": 1,
      "rating": 7,
      "animeId": 3111
    },
    {
      "id": 27181,
      "date": "2019-04-07 21:36:32.291 +00:00",
      "episode": 1,
      "rating": 7,
      "animeId": 3113
    },
    {
      "id": 19728,
      "date": "2019-04-08 15:59:42.598 +00:00",
      "episode": 52,
      "rating": 4,
      "animeId": 2322
    },
    {
      "id": 26806,
      "date": "2019-04-08 16:14:13.342 +00:00",
      "episode": 10,
      "rating": 4,
      "animeId": 3033
    },
    {
      "id": 27186,
      "date": "2019-04-08 16:39:23.188 +00:00",
      "episode": 1,
      "rating": 5,
      "animeId": 3116
    },
    {
      "id": 27196,
      "date": "2019-04-08 17:01:30.745 +00:00",
      "episode": 1,
      "rating": 6,
      "animeId": 3118
    },
    {
      "id": 27201,
      "date": "2019-04-08 17:50:49.824 +00:00",
      "episode": 1,
      "rating": 5,
      "animeId": 3119
    },
    {
      "id": 27206,
      "date": "2019-04-08 18:02:31.207 +00:00",
      "episode": 1,
      "rating": 5,
      "animeId": 3120
    },
    {
      "id": 27191,
      "date": "2019-04-08 21:11:49.601 +00:00",
      "episode": 1,
      "rating": 4,
      "animeId": 3117
    },
    {
      "id": 25990,
      "date": "2019-04-08 21:36:01.963 +00:00",
      "episode": 13,
      "rating": 8,
      "animeId": 2986
    },
    {
      "id": 16109,
      "date": "2019-04-09 15:54:48.166 +00:00",
      "episode": 78,
      "rating": 5,
      "animeId": 1929
    },
    {
      "id": 27211,
      "date": "2019-04-09 16:20:05.530 +00:00",
      "episode": 1,
      "rating": 4,
      "animeId": 3121
    },
    {
      "id": 27216,
      "date": "2019-04-09 16:43:40.149 +00:00",
      "episode": 1,
      "rating": 5,
      "animeId": 3122
    },
    {
      "id": 27093,
      "date": "2019-04-09 17:05:30.961 +00:00",
      "episode": 2,
      "rating": 5,
      "animeId": 3087
    },
    {
      "id": 27107,
      "date": "2019-04-09 17:59:58.977 +00:00",
      "episode": 2,
      "rating": 5,
      "animeId": 3091
    },
    {
      "id": 27221,
      "date": "2019-04-09 21:17:19.279 +00:00",
      "episode": 1,
      "rating": 4,
      "animeId": 3123
    },
    {
      "id": 27226,
      "date": "2019-04-09 21:40:08.688 +00:00",
      "episode": 1,
      "rating": 6,
      "animeId": 3124
    },
    {
      "id": 27230,
      "date": "2019-04-10 15:44:50.256 +00:00",
      "episode": 1,
      "rating": 4,
      "animeId": 3125
    },
    {
      "id": 27234,
      "date": "2019-04-10 15:58:48.488 +00:00",
      "episode": 1,
      "rating": 3,
      "animeId": 3126
    },
    {
      "id": 27238,
      "date": "2019-04-10 16:21:06.864 +00:00",
      "episode": 1,
      "rating": 5,
      "animeId": 3127
    },
    {
      "id": 24403,
      "date": "2019-04-10 16:23:45.832 +00:00",
      "episode": 10,
      "rating": 4,
      "animeId": 2806
    },
    {
      "id": 26295,
      "date": "2019-04-10 16:45:33.249 +00:00",
      "episode": 14,
      "rating": 5,
      "animeId": 3008
    },
    {
      "id": 27242,
      "date": "2019-04-10 21:32:54.747 +00:00",
      "episode": 1,
      "rating": 6,
      "animeId": 3129
    },
    {
      "id": 26861,
      "date": "2019-04-11 15:48:55.142 +00:00",
      "episode": 9,
      "rating": 3,
      "animeId": 3040
    },
    {
      "id": 27249,
      "date": "2019-04-11 17:38:53.064 +00:00",
      "episode": 1,
      "rating": 5,
      "animeId": 3131
    },
    {
      "id": 24624,
      "date": "2019-04-11 17:59:50.815 +00:00",
      "episode": 25,
      "rating": 6,
      "animeId": 2821
    },
    {
      "id": 27253,
      "date": "2019-04-11 21:37:53.011 +00:00",
      "episode": 1,
      "rating": 8,
      "animeId": 3132
    },
    {
      "id": 27257,
      "date": "2019-04-12 15:59:23.945 +00:00",
      "episode": 1,
      "rating": 3,
      "animeId": 3133
    },
    {
      "id": 27262,
      "date": "2019-04-12 17:00:28.649 +00:00",
      "episode": 1,
      "rating": 6,
      "animeId": 3135
    },
    {
      "id": 20822,
      "date": "2019-04-13 15:26:24.346 +00:00",
      "episode": 49,
      "rating": 5,
      "animeId": 2414
    },
    {
      "id": 27132,
      "date": "2019-04-13 15:43:49.177 +00:00",
      "episode": 2,
      "rating": 5,
      "animeId": 3103
    },
    {
      "id": 27137,
      "date": "2019-04-13 15:55:31.149 +00:00",
      "episode": 2,
      "rating": 6,
      "animeId": 3104
    },
    {
      "id": 27152,
      "date": "2019-04-13 16:15:22.226 +00:00",
      "episode": 2,
      "rating": 5,
      "animeId": 3107
    },
    {
      "id": 27127,
      "date": "2019-04-13 16:37:21.427 +00:00",
      "episode": 2,
      "rating": 5,
      "animeId": 3102
    },
    {
      "id": 27142,
      "date": "2019-04-13 17:03:23.210 +00:00",
      "episode": 2,
      "rating": 8,
      "animeId": 3105
    },
    {
      "id": 22705,
      "date": "2019-04-13 19:59:50.324 +00:00",
      "episode": 26,
      "rating": 9,
      "animeId": 2652
    },
    {
      "id": 1538,
      "date": "2019-04-14 14:43:25.754 +00:00",
      "episode": 102,
      "rating": 4,
      "animeId": 122
    },
    {
      "id": 27147,
      "date": "2019-04-14 14:47:13.802 +00:00",
      "episode": 2,
      "rating": 4,
      "animeId": 3106
    },
    {
      "id": 27167,
      "date": "2019-04-14 14:54:29.811 +00:00",
      "episode": 2,
      "rating": 4,
      "animeId": 3110
    },
    {
      "id": 27157,
      "date": "2019-04-14 15:06:20.434 +00:00",
      "episode": 2,
      "rating": 5,
      "animeId": 3108
    },
    {
      "id": 27177,
      "date": "2019-04-14 15:29:29.546 +00:00",
      "episode": 2,
      "rating": 5,
      "animeId": 3112
    },
    {
      "id": 24390,
      "date": "2019-04-14 15:52:50.666 +00:00",
      "episode": 27,
      "rating": 5,
      "animeId": 2805
    },
    {
      "id": 27162,
      "date": "2019-04-14 16:13:45.740 +00:00",
      "episode": 2,
      "rating": 5,
      "animeId": 3109
    },
    {
      "id": 19286,
      "date": "2019-04-14 16:32:07.450 +00:00",
      "episode": 51,
      "rating": 6,
      "animeId": 2306
    },
    {
      "id": 27172,
      "date": "2019-04-14 17:36:42.026 +00:00",
      "episode": 2,
      "rating": 6,
      "animeId": 3111
    },
    {
      "id": 27182,
      "date": "2019-04-14 21:36:38.076 +00:00",
      "episode": 2,
      "rating": 7,
      "animeId": 3113
    },
    {
      "id": 27212,
      "date": "2019-04-15 16:00:57.735 +00:00",
      "episode": 2,
      "rating": 4,
      "animeId": 3121
    },
    {
      "id": 27187,
      "date": "2019-04-15 16:23:07.454 +00:00",
      "episode": 2,
      "rating": 5,
      "animeId": 3116
    },
    {
      "id": 24404,
      "date": "2019-04-15 16:26:58.950 +00:00",
      "episode": 11,
      "rating": 3,
      "animeId": 2806
    },
    {
      "id": 27222,
      "date": "2019-04-15 16:30:08.047 +00:00",
      "episode": 2,
      "rating": 3,
      "animeId": 3123
    },
    {
      "id": 27202,
      "date": "2019-04-15 16:53:35.751 +00:00",
      "episode": 2,
      "rating": 5,
      "animeId": 3119
    },
    {
      "id": 27207,
      "date": "2019-04-15 17:38:17.959 +00:00",
      "episode": 2,
      "rating": 5,
      "animeId": 3120
    },
    {
      "id": 27197,
      "date": "2019-04-15 18:02:20.785 +00:00",
      "episode": 2,
      "rating": 5,
      "animeId": 3118
    },
    {
      "id": 25991,
      "date": "2019-04-15 21:40:34.875 +00:00",
      "episode": 14,
      "rating": 7,
      "animeId": 2986
    },
    {
      "id": 27282,
      "date": "2019-04-16 16:03:52.175 +00:00",
      "episode": 1,
      "rating": 3,
      "animeId": 3142
    },
    {
      "id": 16110,
      "date": "2019-04-16 16:27:45.159 +00:00",
      "episode": 79,
      "rating": 4,
      "animeId": 1929
    },
    {
      "id": 27217,
      "date": "2019-04-16 16:49:09.864 +00:00",
      "episode": 2,
      "rating": 5,
      "animeId": 3122
    },
    {
      "id": 27094,
      "date": "2019-04-16 17:11:10.090 +00:00",
      "episode": 3,
      "rating": 5,
      "animeId": 3087
    },
    {
      "id": 27227,
      "date": "2019-04-16 21:33:53.375 +00:00",
      "episode": 2,
      "rating": 7,
      "animeId": 3124
    },
    {
      "id": 27235,
      "date": "2019-04-17 15:42:23.733 +00:00",
      "episode": 2,
      "rating": 3,
      "animeId": 3126
    },
    {
      "id": 27231,
      "date": "2019-04-17 15:53:12.610 +00:00",
      "episode": 2,
      "rating": 5,
      "animeId": 3125
    },
    {
      "id": 27108,
      "date": "2019-04-17 16:17:25.359 +00:00",
      "episode": 3,
      "rating": 5,
      "animeId": 3091
    },
    {
      "id": 26296,
      "date": "2019-04-17 17:39:28.334 +00:00",
      "episode": 15,
      "rating": 6,
      "animeId": 3008
    },
    {
      "id": 27239,
      "date": "2019-04-17 18:01:05.070 +00:00",
      "episode": 2,
      "rating": 6,
      "animeId": 3127
    },
    {
      "id": 27243,
      "date": "2019-04-17 21:32:39.471 +00:00",
      "episode": 2,
      "rating": 6,
      "animeId": 3129
    },
    {
      "id": 26862,
      "date": "2019-04-18 15:46:29.756 +00:00",
      "episode": 10,
      "rating": 3,
      "animeId": 3040
    },
    {
      "id": 21458,
      "date": "2019-04-18 15:57:32.214 +00:00",
      "episode": 10,
      "rating": 4,
      "animeId": 2515
    },
    {
      "id": 27250,
      "date": "2019-04-18 17:34:52.096 +00:00",
      "episode": 2,
      "rating": 5,
      "animeId": 3131
    },
    {
      "id": 24625,
      "date": "2019-04-18 17:58:41.535 +00:00",
      "episode": 26,
      "rating": 5,
      "animeId": 2821
    },
    {
      "id": 27254,
      "date": "2019-04-18 21:36:02.995 +00:00",
      "episode": 2,
      "rating": 7,
      "animeId": 3132
    },
    {
      "id": 27258,
      "date": "2019-04-19 16:42:31.081 +00:00",
      "episode": 2,
      "rating": 3,
      "animeId": 3133
    },
    {
      "id": 27263,
      "date": "2019-04-19 17:08:56.652 +00:00",
      "episode": 2,
      "rating": 6,
      "animeId": 3135
    },
    {
      "id": 26807,
      "date": "2019-04-20 14:34:38.632 +00:00",
      "episode": 11,
      "rating": 4,
      "animeId": 3033
    },
    {
      "id": 26808,
      "date": "2019-04-20 14:50:22.569 +00:00",
      "episode": 12,
      "rating": 4,
      "animeId": 3033
    },
    {
      "id": 20823,
      "date": "2019-04-20 15:09:20.867 +00:00",
      "episode": 50,
      "rating": 4,
      "animeId": 2414
    },
    {
      "id": 27153,
      "date": "2019-04-20 15:31:58.806 +00:00",
      "episode": 3,
      "rating": 4,
      "animeId": 3107
    },
    {
      "id": 27133,
      "date": "2019-04-20 15:45:56.456 +00:00",
      "episode": 3,
      "rating": 5,
      "animeId": 3103
    },
    {
      "id": 27138,
      "date": "2019-04-20 15:57:19.710 +00:00",
      "episode": 3,
      "rating": 6,
      "animeId": 3104
    },
    {
      "id": 27128,
      "date": "2019-04-20 16:19:42.621 +00:00",
      "episode": 3,
      "rating": 5,
      "animeId": 3102
    },
    {
      "id": 27143,
      "date": "2019-04-20 16:48:25.311 +00:00",
      "episode": 3,
      "rating": 8,
      "animeId": 3105
    },
    {
      "id": 22706,
      "date": "2019-04-20 19:59:42.931 +00:00",
      "episode": 27,
      "rating": 9,
      "animeId": 2652
    },
    {
      "id": 1539,
      "date": "2019-04-21 14:42:06.190 +00:00",
      "episode": 103,
      "rating": 4,
      "animeId": 122
    },
    {
      "id": 27148,
      "date": "2019-04-21 14:59:56.550 +00:00",
      "episode": 3,
      "rating": 5,
      "animeId": 3106
    },
    {
      "id": 27168,
      "date": "2019-04-21 15:06:51.784 +00:00",
      "episode": 3,
      "rating": 4,
      "animeId": 3110
    },
    {
      "id": 27158,
      "date": "2019-04-21 15:18:25.930 +00:00",
      "episode": 3,
      "rating": 4,
      "animeId": 3108
    },
    {
      "id": 27178,
      "date": "2019-04-21 15:40:14.706 +00:00",
      "episode": 3,
      "rating": 5,
      "animeId": 3112
    },
    {
      "id": 24391,
      "date": "2019-04-21 16:00:14.858 +00:00",
      "episode": 28,
      "rating": 5,
      "animeId": 2805
    },
    {
      "id": 27163,
      "date": "2019-04-21 16:23:01.209 +00:00",
      "episode": 3,
      "rating": 5,
      "animeId": 3109
    },
    {
      "id": 19287,
      "date": "2019-04-21 16:46:28.721 +00:00",
      "episode": 52,
      "rating": 5,
      "animeId": 2306
    },
    {
      "id": 27173,
      "date": "2019-04-21 17:09:07.440 +00:00",
      "episode": 3,
      "rating": 7,
      "animeId": 3111
    },
    {
      "id": 27183,
      "date": "2019-04-21 21:35:54.633 +00:00",
      "episode": 3,
      "rating": 6,
      "animeId": 3113
    },
    {
      "id": 27192,
      "date": "2019-04-22 05:13:49.452 +00:00",
      "episode": 2,
      "rating": 3,
      "animeId": 3117
    },
    {
      "id": 27193,
      "date": "2019-04-22 05:13:49.453 +00:00",
      "episode": 3,
      "rating": 3,
      "animeId": 3117
    },
    {
      "id": 27223,
      "date": "2019-04-22 15:21:23.575 +00:00",
      "episode": 3,
      "rating": 3,
      "animeId": 3123
    },
    {
      "id": 27213,
      "date": "2019-04-22 15:48:50.911 +00:00",
      "episode": 3,
      "rating": 4,
      "animeId": 3121
    },
    {
      "id": 27188,
      "date": "2019-04-22 16:11:45.897 +00:00",
      "episode": 3,
      "rating": 4,
      "animeId": 3116
    },
    {
      "id": 27203,
      "date": "2019-04-22 16:37:20.296 +00:00",
      "episode": 3,
      "rating": 4,
      "animeId": 3119
    },
    {
      "id": 27208,
      "date": "2019-04-22 16:47:10.329 +00:00",
      "episode": 3,
      "rating": 6,
      "animeId": 3120
    },
    {
      "id": 27198,
      "date": "2019-04-22 17:34:39.979 +00:00",
      "episode": 3,
      "rating": 6,
      "animeId": 3118
    },
    {
      "id": 25992,
      "date": "2019-04-22 21:36:53.763 +00:00",
      "episode": 15,
      "rating": 7,
      "animeId": 2986
    },
    {
      "id": 27283,
      "date": "2019-04-23 15:58:00.678 +00:00",
      "episode": 2,
      "rating": 3,
      "animeId": 3142
    },
    {
      "id": 16111,
      "date": "2019-04-23 16:19:34.260 +00:00",
      "episode": 80,
      "rating": 4,
      "animeId": 1929
    },
    {
      "id": 27218,
      "date": "2019-04-23 17:44:08.927 +00:00",
      "episode": 3,
      "rating": 4,
      "animeId": 3122
    },
    {
      "id": 27095,
      "date": "2019-04-23 18:05:09.000 +00:00",
      "episode": 4,
      "rating": 5,
      "animeId": 3087
    },
    {
      "id": 27228,
      "date": "2019-04-23 21:32:39.472 +00:00",
      "episode": 3,
      "rating": 7,
      "animeId": 3124
    },
    {
      "id": 27236,
      "date": "2019-04-24 15:45:26.819 +00:00",
      "episode": 3,
      "rating": 2,
      "animeId": 3126
    },
    {
      "id": 27232,
      "date": "2019-04-24 15:59:28.584 +00:00",
      "episode": 3,
      "rating": 4,
      "animeId": 3125
    },
    {
      "id": 27109,
      "date": "2019-04-24 16:22:15.632 +00:00",
      "episode": 4,
      "rating": 5,
      "animeId": 3091
    },
    {
      "id": 26297,
      "date": "2019-04-24 17:38:10.762 +00:00",
      "episode": 16,
      "rating": 5,
      "animeId": 3008
    },
    {
      "id": 27240,
      "date": "2019-04-24 17:59:45.389 +00:00",
      "episode": 3,
      "rating": 6,
      "animeId": 3127
    },
    {
      "id": 27244,
      "date": "2019-04-24 21:37:36.769 +00:00",
      "episode": 3,
      "rating": 6,
      "animeId": 3129
    },
    {
      "id": 26863,
      "date": "2019-04-25 15:43:57.994 +00:00",
      "episode": 11,
      "rating": 3,
      "animeId": 3040
    },
    {
      "id": 26358,
      "date": "2019-04-25 16:03:25.536 +00:00",
      "episode": 10,
      "rating": 4,
      "animeId": 3014
    },
    {
      "id": 26359,
      "date": "2019-04-25 16:20:31.962 +00:00",
      "episode": 11,
      "rating": 4,
      "animeId": 3014
    },
    {
      "id": 27251,
      "date": "2019-04-25 17:28:53.258 +00:00",
      "episode": 3,
      "rating": 5,
      "animeId": 3131
    },
    {
      "id": 24626,
      "date": "2019-04-25 17:52:40.531 +00:00",
      "episode": 27,
      "rating": 6,
      "animeId": 2821
    },
    {
      "id": 27255,
      "date": "2019-04-25 21:37:07.040 +00:00",
      "episode": 3,
      "rating": 6,
      "animeId": 3132
    },
    {
      "id": 27259,
      "date": "2019-04-26 15:55:27.167 +00:00",
      "episode": 3,
      "rating": 4,
      "animeId": 3133
    },
    {
      "id": 27264,
      "date": "2019-04-26 17:00:18.320 +00:00",
      "episode": 3,
      "rating": 7,
      "animeId": 3135
    },
    {
      "id": 27154,
      "date": "2019-04-27 15:36:13.100 +00:00",
      "episode": 4,
      "rating": 4,
      "animeId": 3107
    },
    {
      "id": 20824,
      "date": "2019-04-27 15:52:26.257 +00:00",
      "episode": 51,
      "rating": 5,
      "animeId": 2414
    },
    {
      "id": 27134,
      "date": "2019-04-27 16:05:21.145 +00:00",
      "episode": 4,
      "rating": 5,
      "animeId": 3103
    },
    {
      "id": 27139,
      "date": "2019-04-27 16:18:44.300 +00:00",
      "episode": 4,
      "rating": 5,
      "animeId": 3104
    },
    {
      "id": 27129,
      "date": "2019-04-27 16:43:01.739 +00:00",
      "episode": 4,
      "rating": 6,
      "animeId": 3102
    },
    {
      "id": 27144,
      "date": "2019-04-27 17:07:11.410 +00:00",
      "episode": 4,
      "rating": 7,
      "animeId": 3105
    },
    {
      "id": 22707,
      "date": "2019-04-27 20:15:00.193 +00:00",
      "episode": 28,
      "rating": 9,
      "animeId": 2652
    },
    {
      "id": 1540,
      "date": "2019-04-28 14:41:10.103 +00:00",
      "episode": 104,
      "rating": 4,
      "animeId": 122
    },
    {
      "id": 27149,
      "date": "2019-04-28 14:44:54.591 +00:00",
      "episode": 4,
      "rating": 4,
      "animeId": 3106
    },
    {
      "id": 27169,
      "date": "2019-04-28 14:53:26.072 +00:00",
      "episode": 4,
      "rating": 5,
      "animeId": 3110
    },
    {
      "id": 27179,
      "date": "2019-04-28 15:16:56.232 +00:00",
      "episode": 4,
      "rating": 5,
      "animeId": 3112
    },
    {
      "id": 27159,
      "date": "2019-04-28 15:39:49.384 +00:00",
      "episode": 4,
      "rating": 5,
      "animeId": 3108
    },
    {
      "id": 24392,
      "date": "2019-04-28 15:57:55.360 +00:00",
      "episode": 29,
      "rating": 5,
      "animeId": 2805
    },
    {
      "id": 27164,
      "date": "2019-04-28 16:20:35.298 +00:00",
      "episode": 4,
      "rating": 5,
      "animeId": 3109
    },
    {
      "id": 19288,
      "date": "2019-04-28 16:37:29.864 +00:00",
      "episode": 53,
      "rating": 5,
      "animeId": 2306
    },
    {
      "id": 27174,
      "date": "2019-04-28 17:44:13.689 +00:00",
      "episode": 4,
      "rating": 8,
      "animeId": 3111
    },
    {
      "id": 27184,
      "date": "2019-04-28 21:37:54.099 +00:00",
      "episode": 4,
      "rating": 7,
      "animeId": 3113
    },
    {
      "id": 27194,
      "date": "2019-04-29 15:11:48.265 +00:00",
      "episode": 4,
      "rating": 4,
      "animeId": 3117
    },
    {
      "id": 27224,
      "date": "2019-04-29 15:31:26.875 +00:00",
      "episode": 4,
      "rating": 3,
      "animeId": 3123
    },
    {
      "id": 27189,
      "date": "2019-04-29 15:53:48.266 +00:00",
      "episode": 4,
      "rating": 5,
      "animeId": 3116
    },
    {
      "id": 27204,
      "date": "2019-04-29 16:16:47.875 +00:00",
      "episode": 4,
      "rating": 3,
      "animeId": 3119
    },
    {
      "id": 27209,
      "date": "2019-04-29 16:31:30.859 +00:00",
      "episode": 4,
      "rating": 4,
      "animeId": 3120
    },
    {
      "id": 27199,
      "date": "2019-04-29 16:54:21.475 +00:00",
      "episode": 4,
      "rating": 6,
      "animeId": 3118
    },
    {
      "id": 27487,
      "date": "2019-04-29 17:48:05.802 +00:00",
      "episode": 1,
      "rating": 7,
      "animeId": 3185
    },
    {
      "id": 25993,
      "date": "2019-04-29 21:35:45.221 +00:00",
      "episode": 16,
      "rating": 7,
      "animeId": 2986
    },
    {
      "id": 27284,
      "date": "2019-04-30 16:03:31.567 +00:00",
      "episode": 3,
      "rating": 3,
      "animeId": 3142
    },
    {
      "id": 27214,
      "date": "2019-04-30 16:20:10.248 +00:00",
      "episode": 4,
      "rating": 4,
      "animeId": 3121
    },
    {
      "id": 16112,
      "date": "2019-04-30 16:56:35.476 +00:00",
      "episode": 81,
      "rating": 5,
      "animeId": 1929
    },
    {
      "id": 27219,
      "date": "2019-04-30 17:14:54.224 +00:00",
      "episode": 4,
      "rating": 4,
      "animeId": 3122
    },
    {
      "id": 27096,
      "date": "2019-04-30 18:01:03.608 +00:00",
      "episode": 5,
      "rating": 4,
      "animeId": 3087
    },
    {
      "id": 27229,
      "date": "2019-04-30 21:38:15.360 +00:00",
      "episode": 4,
      "rating": 6,
      "animeId": 3124
    },
    {
      "id": 27237,
      "date": "2019-05-01 15:54:59.010 +00:00",
      "episode": 4,
      "rating": 3,
      "animeId": 3126
    },
    {
      "id": 27110,
      "date": "2019-05-01 16:18:49.217 +00:00",
      "episode": 5,
      "rating": 5,
      "animeId": 3091
    },
    {
      "id": 27233,
      "date": "2019-05-01 16:29:53.712 +00:00",
      "episode": 4,
      "rating": 5,
      "animeId": 3125
    },
    {
      "id": 26298,
      "date": "2019-05-01 17:39:17.123 +00:00",
      "episode": 17,
      "rating": 5,
      "animeId": 3008
    },
    {
      "id": 27241,
      "date": "2019-05-01 18:02:09.851 +00:00",
      "episode": 4,
      "rating": 6,
      "animeId": 3127
    },
    {
      "id": 27245,
      "date": "2019-05-01 21:35:18.359 +00:00",
      "episode": 4,
      "rating": 6,
      "animeId": 3129
    },
    {
      "id": 24405,
      "date": "2019-05-02 15:44:59.902 +00:00",
      "episode": 12,
      "rating": 4,
      "animeId": 2806
    },
    {
      "id": 24406,
      "date": "2019-05-02 15:44:59.903 +00:00",
      "episode": 13,
      "rating": 5,
      "animeId": 2806
    },
    {
      "id": 24407,
      "date": "2019-05-02 15:44:59.904 +00:00",
      "episode": 14,
      "rating": 5,
      "animeId": 2806
    },
    {
      "id": 26864,
      "date": "2019-05-02 15:52:07.935 +00:00",
      "episode": 12,
      "rating": 3,
      "animeId": 3040
    },
    {
      "id": 27252,
      "date": "2019-05-02 16:51:21.620 +00:00",
      "episode": 4,
      "rating": 5,
      "animeId": 3131
    },
    {
      "id": 24627,
      "date": "2019-05-02 17:32:03.347 +00:00",
      "episode": 28,
      "rating": 6,
      "animeId": 2821
    },
    {
      "id": 27256,
      "date": "2019-05-02 21:33:06.235 +00:00",
      "episode": 4,
      "rating": 6,
      "animeId": 3132
    },
    {
      "id": 27260,
      "date": "2019-05-03 16:22:26.903 +00:00",
      "episode": 4,
      "rating": 5,
      "animeId": 3133
    },
    {
      "id": 27265,
      "date": "2019-05-03 17:03:59.531 +00:00",
      "episode": 4,
      "rating": 7,
      "animeId": 3135
    },
    {
      "id": 27155,
      "date": "2019-05-04 15:25:39.322 +00:00",
      "episode": 5,
      "rating": 4,
      "animeId": 3107
    },
    {
      "id": 20825,
      "date": "2019-05-04 15:34:54.126 +00:00",
      "episode": 52,
      "rating": 3,
      "animeId": 2414
    },
    {
      "id": 27135,
      "date": "2019-05-04 15:56:25.668 +00:00",
      "episode": 5,
      "rating": 5,
      "animeId": 3103
    },
    {
      "id": 27130,
      "date": "2019-05-04 16:17:21.828 +00:00",
      "episode": 5,
      "rating": 6,
      "animeId": 3102
    },
    {
      "id": 27140,
      "date": "2019-05-04 16:30:53.398 +00:00",
      "episode": 5,
      "rating": 6,
      "animeId": 3104
    },
    {
      "id": 27145,
      "date": "2019-05-04 17:10:41.616 +00:00",
      "episode": 5,
      "rating": 6,
      "animeId": 3105
    },
    {
      "id": 1541,
      "date": "2019-05-05 14:40:35.012 +00:00",
      "episode": 105,
      "rating": 2,
      "animeId": 122
    },
    {
      "id": 27150,
      "date": "2019-05-05 14:44:13.840 +00:00",
      "episode": 5,
      "rating": 4,
      "animeId": 3106
    },
    {
      "id": 27170,
      "date": "2019-05-05 14:51:57.401 +00:00",
      "episode": 5,
      "rating": 4,
      "animeId": 3110
    },
    {
      "id": 27160,
      "date": "2019-05-05 15:04:02.274 +00:00",
      "episode": 5,
      "rating": 4,
      "animeId": 3108
    },
    {
      "id": 27180,
      "date": "2019-05-05 15:41:20.016 +00:00",
      "episode": 5,
      "rating": 7,
      "animeId": 3112
    },
    {
      "id": 24393,
      "date": "2019-05-05 16:02:53.922 +00:00",
      "episode": 30,
      "rating": 6,
      "animeId": 2805
    },
    {
      "id": 27165,
      "date": "2019-05-05 16:26:52.127 +00:00",
      "episode": 5,
      "rating": 5,
      "animeId": 3109
    },
    {
      "id": 19289,
      "date": "2019-05-05 16:48:45.754 +00:00",
      "episode": 54,
      "rating": 5,
      "animeId": 2306
    },
    {
      "id": 27175,
      "date": "2019-05-05 17:11:25.011 +00:00",
      "episode": 5,
      "rating": 7,
      "animeId": 3111
    },
    {
      "id": 27185,
      "date": "2019-05-05 21:40:44.680 +00:00",
      "episode": 5,
      "rating": 6,
      "animeId": 3113
    },
    {
      "id": 27195,
      "date": "2019-05-06 14:03:30.560 +00:00",
      "episode": 5,
      "rating": 3,
      "animeId": 3117
    },
    {
      "id": 27225,
      "date": "2019-05-06 14:30:32.414 +00:00",
      "episode": 5,
      "rating": 3,
      "animeId": 3123
    },
    {
      "id": 27205,
      "date": "2019-05-06 14:53:24.199 +00:00",
      "episode": 5,
      "rating": 4,
      "animeId": 3119
    },
    {
      "id": 27190,
      "date": "2019-05-06 15:17:02.833 +00:00",
      "episode": 5,
      "rating": 4,
      "animeId": 3116
    },
    {
      "id": 27210,
      "date": "2019-05-06 16:33:34.818 +00:00",
      "episode": 5,
      "rating": 5,
      "animeId": 3120
    },
    {
      "id": 27200,
      "date": "2019-05-06 16:55:59.608 +00:00",
      "episode": 5,
      "rating": 6,
      "animeId": 3118
    },
    {
      "id": 27488,
      "date": "2019-05-06 17:52:25.755 +00:00",
      "episode": 2,
      "rating": 7,
      "animeId": 3185
    },
    {
      "id": 25994,
      "date": "2019-05-06 21:35:46.792 +00:00",
      "episode": 17,
      "rating": 7,
      "animeId": 2986
    },
    {
      "id": 27285,
      "date": "2019-05-07 15:54:45.699 +00:00",
      "episode": 4,
      "rating": 4,
      "animeId": 3142
    },
    {
      "id": 27215,
      "date": "2019-05-07 16:25:42.843 +00:00",
      "episode": 5,
      "rating": 4,
      "animeId": 3121
    },
    {
      "id": 27220,
      "date": "2019-05-07 16:47:19.485 +00:00",
      "episode": 5,
      "rating": 5,
      "animeId": 3122
    },
    {
      "id": 16113,
      "date": "2019-05-07 17:03:57.771 +00:00",
      "episode": 82,
      "rating": 3,
      "animeId": 1929
    },
    {
      "id": 27097,
      "date": "2019-05-07 17:59:31.160 +00:00",
      "episode": 6,
      "rating": 5,
      "animeId": 3087
    },
    {
      "id": 27490,
      "date": "2019-05-07 21:31:50.789 +00:00",
      "episode": 5,
      "rating": 6,
      "animeId": 3124
    },
    {
      "id": 27499,
      "date": "2019-05-08 15:45:24.737 +00:00",
      "episode": 5,
      "rating": 3,
      "animeId": 3126
    },
    {
      "id": 27500,
      "date": "2019-05-08 16:06:26.698 +00:00",
      "episode": 6,
      "rating": 6,
      "animeId": 3091
    },
    {
      "id": 27501,
      "date": "2019-05-08 16:18:40.970 +00:00",
      "episode": 5,
      "rating": 5,
      "animeId": 3125
    },
    {
      "id": 27503,
      "date": "2019-05-08 17:36:29.788 +00:00",
      "episode": 18,
      "rating": 6,
      "animeId": 3008
    },
    {
      "id": 27504,
      "date": "2019-05-08 17:58:30.828 +00:00",
      "episode": 5,
      "rating": 6,
      "animeId": 3127
    },
    {
      "id": 27505,
      "date": "2019-05-08 21:33:14.917 +00:00",
      "episode": 5,
      "rating": 5,
      "animeId": 3129
    },
    {
      "id": 27513,
      "date": "2019-05-09 15:50:13.436 +00:00",
      "episode": 13,
      "rating": 3,
      "animeId": 3040
    },
    {
      "id": 27514,
      "date": "2019-05-09 15:59:13.774 +00:00",
      "episode": 11,
      "rating": 4,
      "animeId": 2515
    },
    {
      "id": 27518,
      "date": "2019-05-09 17:44:04.164 +00:00",
      "episode": 5,
      "rating": 5,
      "animeId": 3131
    },
    {
      "id": 27520,
      "date": "2019-05-09 21:37:54.501 +00:00",
      "episode": 5,
      "rating": 6,
      "animeId": 3132
    },
    {
      "id": 27529,
      "date": "2019-05-10 15:57:05.420 +00:00",
      "episode": 5,
      "rating": 4,
      "animeId": 3133
    },
    {
      "id": 27531,
      "date": "2019-05-10 16:56:56.725 +00:00",
      "episode": 5,
      "rating": 6,
      "animeId": 3135
    },
    {
      "id": 27562,
      "date": "2019-05-11 15:36:05.893 +00:00",
      "episode": 6,
      "rating": 4,
      "animeId": 3107
    },
    {
      "id": 27563,
      "date": "2019-05-11 15:57:08.691 +00:00",
      "episode": 1,
      "rating": 5,
      "animeId": 3216
    },
    {
      "id": 27564,
      "date": "2019-05-11 16:12:56.356 +00:00",
      "episode": 6,
      "rating": 6,
      "animeId": 3103
    },
    {
      "id": 27565,
      "date": "2019-05-11 16:33:38.388 +00:00",
      "episode": 6,
      "rating": 6,
      "animeId": 3102
    },
    {
      "id": 27566,
      "date": "2019-05-11 16:38:37.017 +00:00",
      "episode": 1,
      "rating": 6,
      "animeId": 3212
    },
    {
      "id": 27567,
      "date": "2019-05-11 16:50:23.122 +00:00",
      "episode": 6,
      "rating": 6,
      "animeId": 3104
    },
    {
      "id": 27568,
      "date": "2019-05-11 17:13:22.475 +00:00",
      "episode": 6,
      "rating": 7,
      "animeId": 3105
    },
    {
      "id": 27569,
      "date": "2019-05-11 20:03:04.434 +00:00",
      "episode": 29,
      "rating": 8,
      "animeId": 2652
    },
    {
      "id": 27597,
      "date": "2019-05-12 14:38:54.234 +00:00",
      "episode": 106,
      "rating": 4,
      "animeId": 122
    },
    {
      "id": 27598,
      "date": "2019-05-12 15:29:04.511 +00:00",
      "episode": 6,
      "rating": 5,
      "animeId": 3106
    },
    {
      "id": 27599,
      "date": "2019-05-12 15:34:37.524 +00:00",
      "episode": 6,
      "rating": 4,
      "animeId": 3110
    },
    {
      "id": 27600,
      "date": "2019-05-12 15:43:39.224 +00:00",
      "episode": 6,
      "rating": 4,
      "animeId": 3108
    },
    {
      "id": 27601,
      "date": "2019-05-12 16:01:27.397 +00:00",
      "episode": 6,
      "rating": 6,
      "animeId": 3112
    },
    {
      "id": 27602,
      "date": "2019-05-12 16:19:16.673 +00:00",
      "episode": 31,
      "rating": 5,
      "animeId": 2805
    },
    {
      "id": 27603,
      "date": "2019-05-12 16:41:52.239 +00:00",
      "episode": 6,
      "rating": 6,
      "animeId": 3109
    },
    {
      "id": 27604,
      "date": "2019-05-12 16:56:59.284 +00:00",
      "episode": 55,
      "rating": 5,
      "animeId": 2306
    },
    {
      "id": 27605,
      "date": "2019-05-12 17:52:27.089 +00:00",
      "episode": 6,
      "rating": 7,
      "animeId": 3111
    },
    {
      "id": 27606,
      "date": "2019-05-12 21:35:02.546 +00:00",
      "episode": 6,
      "rating": 6,
      "animeId": 3113
    },
    {
      "id": 27630,
      "date": "2019-05-13 11:09:21.301 +00:00",
      "episode": 6,
      "rating": 3,
      "animeId": 3117
    },
    {
      "id": 27634,
      "date": "2019-05-13 14:37:39.112 +00:00",
      "episode": 6,
      "rating": 4,
      "animeId": 3123
    },
    {
      "id": 27635,
      "date": "2019-05-13 15:00:46.727 +00:00",
      "episode": 6,
      "rating": 3,
      "animeId": 3119
    },
    {
      "id": 27636,
      "date": "2019-05-13 15:22:14.428 +00:00",
      "episode": 6,
      "rating": 4,
      "animeId": 3116
    },
    {
      "id": 27638,
      "date": "2019-05-13 16:49:03.959 +00:00",
      "episode": 6,
      "rating": 5,
      "animeId": 3120
    },
    {
      "id": 27639,
      "date": "2019-05-13 17:33:15.213 +00:00",
      "episode": 6,
      "rating": 6,
      "animeId": 3118
    },
    {
      "id": 27640,
      "date": "2019-05-13 17:56:39.731 +00:00",
      "episode": 3,
      "rating": 7,
      "animeId": 3185
    },
    {
      "id": 27641,
      "date": "2019-05-13 21:34:14.362 +00:00",
      "episode": 18,
      "rating": 7,
      "animeId": 2986
    },
    {
      "id": 27650,
      "date": "2019-05-14 15:57:26.366 +00:00",
      "episode": 5,
      "rating": 4,
      "animeId": 3142
    },
    {
      "id": 27651,
      "date": "2019-05-14 16:15:55.844 +00:00",
      "episode": 6,
      "rating": 4,
      "animeId": 3121
    },
    {
      "id": 27652,
      "date": "2019-05-14 16:32:38.240 +00:00",
      "episode": 7,
      "rating": 5,
      "animeId": 3087
    },
    {
      "id": 27654,
      "date": "2019-05-14 17:07:11.798 +00:00",
      "episode": 83,
      "rating": 5,
      "animeId": 1929
    },
    {
      "id": 27655,
      "date": "2019-05-14 18:00:10.835 +00:00",
      "episode": 6,
      "rating": 5,
      "animeId": 3122
    },
    {
      "id": 27656,
      "date": "2019-05-14 21:31:33.867 +00:00",
      "episode": 6,
      "rating": 6,
      "animeId": 3124
    },
    {
      "id": 27664,
      "date": "2019-05-15 15:44:47.961 +00:00",
      "episode": 6,
      "rating": 4,
      "animeId": 3126
    },
    {
      "id": 27665,
      "date": "2019-05-15 16:08:00.140 +00:00",
      "episode": 7,
      "rating": 5,
      "animeId": 3091
    },
    {
      "id": 27666,
      "date": "2019-05-15 16:17:01.180 +00:00",
      "episode": 6,
      "rating": 5,
      "animeId": 3125
    },
    {
      "id": 27668,
      "date": "2019-05-15 17:38:59.081 +00:00",
      "episode": 19,
      "rating": 5,
      "animeId": 3008
    },
    {
      "id": 27669,
      "date": "2019-05-15 18:03:23.556 +00:00",
      "episode": 6,
      "rating": 6,
      "animeId": 3127
    },
    {
      "id": 27670,
      "date": "2019-05-15 21:41:58.907 +00:00",
      "episode": 6,
      "rating": 6,
      "animeId": 3129
    },
    {
      "id": 27678,
      "date": "2019-05-16 15:44:48.553 +00:00",
      "episode": 14,
      "rating": 4,
      "animeId": 3040
    },
    {
      "id": 27683,
      "date": "2019-05-16 17:38:20.111 +00:00",
      "episode": 6,
      "rating": 5,
      "animeId": 3131
    },
    {
      "id": 27684,
      "date": "2019-05-16 18:02:51.815 +00:00",
      "episode": 29,
      "rating": 6,
      "animeId": 2821
    },
    {
      "id": 27685,
      "date": "2019-05-16 21:33:06.734 +00:00",
      "episode": 6,
      "rating": 6,
      "animeId": 3132
    },
    {
      "id": 27694,
      "date": "2019-05-17 16:32:45.252 +00:00",
      "episode": 6,
      "rating": 4,
      "animeId": 3133
    },
    {
      "id": 27695,
      "date": "2019-05-17 16:57:20.569 +00:00",
      "episode": 6,
      "rating": 6,
      "animeId": 3135
    },
    {
      "id": 27725,
      "date": "2019-05-18 15:37:27.845 +00:00",
      "episode": 7,
      "rating": 4,
      "animeId": 3107
    },
    {
      "id": 27726,
      "date": "2019-05-18 15:56:13.840 +00:00",
      "episode": 2,
      "rating": 4,
      "animeId": 3216
    },
    {
      "id": 27727,
      "date": "2019-05-18 16:06:45.654 +00:00",
      "episode": 7,
      "rating": 5,
      "animeId": 3103
    },
    {
      "id": 27728,
      "date": "2019-05-18 16:26:27.347 +00:00",
      "episode": 7,
      "rating": 5,
      "animeId": 3102
    },
    {
      "id": 27729,
      "date": "2019-05-18 17:07:19.929 +00:00",
      "episode": 2,
      "rating": 5,
      "animeId": 3212
    },
    {
      "id": 27730,
      "date": "2019-05-18 17:18:00.527 +00:00",
      "episode": 7,
      "rating": 6,
      "animeId": 3104
    },
    {
      "id": 27731,
      "date": "2019-05-18 17:41:29.252 +00:00",
      "episode": 7,
      "rating": 6,
      "animeId": 3105
    },
    {
      "id": 27732,
      "date": "2019-05-18 20:01:57.338 +00:00",
      "episode": 30,
      "rating": 8,
      "animeId": 2652
    },
    {
      "id": 27762,
      "date": "2019-05-19 14:36:20.230 +00:00",
      "episode": 107,
      "rating": 4,
      "animeId": 122
    },
    {
      "id": 27766,
      "date": "2019-05-19 15:28:54.054 +00:00",
      "episode": 12,
      "rating": 4,
      "animeId": 3014
    },
    {
      "id": 27767,
      "date": "2019-05-19 15:33:07.454 +00:00",
      "episode": 7,
      "rating": 4,
      "animeId": 3106
    },
    {
      "id": 27768,
      "date": "2019-05-19 15:41:20.767 +00:00",
      "episode": 7,
      "rating": 5,
      "animeId": 3110
    },
    {
      "id": 27769,
      "date": "2019-05-19 15:50:24.035 +00:00",
      "episode": 7,
      "rating": 5,
      "animeId": 3108
    },
    {
      "id": 27770,
      "date": "2019-05-19 16:12:42.083 +00:00",
      "episode": 7,
      "rating": 6,
      "animeId": 3112
    },
    {
      "id": 27771,
      "date": "2019-05-19 16:27:12.597 +00:00",
      "episode": 32,
      "rating": 5,
      "animeId": 2805
    },
    {
      "id": 27772,
      "date": "2019-05-19 16:50:31.654 +00:00",
      "episode": 7,
      "rating": 6,
      "animeId": 3109
    },
    {
      "id": 27773,
      "date": "2019-05-19 17:32:53.012 +00:00",
      "episode": 56,
      "rating": 6,
      "animeId": 2306
    },
    {
      "id": 27774,
      "date": "2019-05-19 17:55:48.306 +00:00",
      "episode": 7,
      "rating": 7,
      "animeId": 3111
    },
    {
      "id": 27775,
      "date": "2019-05-19 21:28:16.388 +00:00",
      "episode": 7,
      "rating": 6,
      "animeId": 3113
    },
    {
      "id": 27802,
      "date": "2019-05-20 13:57:07.705 +00:00",
      "episode": 7,
      "rating": 4,
      "animeId": 3117
    },
    {
      "id": 27803,
      "date": "2019-05-20 14:01:02.980 +00:00",
      "episode": 15,
      "rating": 3,
      "animeId": 2806
    },
    {
      "id": 27804,
      "date": "2019-05-20 14:01:02.981 +00:00",
      "episode": 16,
      "rating": 5,
      "animeId": 2806
    },
    {
      "id": 27807,
      "date": "2019-05-20 14:38:50.875 +00:00",
      "episode": 7,
      "rating": 3,
      "animeId": 3123
    },
    {
      "id": 27809,
      "date": "2019-05-20 16:11:08.089 +00:00",
      "episode": 7,
      "rating": 4,
      "animeId": 3119
    },
    {
      "id": 27810,
      "date": "2019-05-20 16:28:51.056 +00:00",
      "episode": 7,
      "rating": 4,
      "animeId": 3116
    },
    {
      "id": 27811,
      "date": "2019-05-20 16:38:21.939 +00:00",
      "episode": 7,
      "rating": 6,
      "animeId": 3120
    },
    {
      "id": 27812,
      "date": "2019-05-20 17:26:48.785 +00:00",
      "episode": 7,
      "rating": 6,
      "animeId": 3118
    },
    {
      "id": 27813,
      "date": "2019-05-20 17:48:38.152 +00:00",
      "episode": 4,
      "rating": 8,
      "animeId": 3185
    },
    {
      "id": 27814,
      "date": "2019-05-20 21:35:19.550 +00:00",
      "episode": 19,
      "rating": 6,
      "animeId": 2986
    },
    {
      "id": 27823,
      "date": "2019-05-21 15:57:29.566 +00:00",
      "episode": 6,
      "rating": 4,
      "animeId": 3142
    },
    {
      "id": 27824,
      "date": "2019-05-21 16:15:48.981 +00:00",
      "episode": 7,
      "rating": 4,
      "animeId": 3121
    },
    {
      "id": 27826,
      "date": "2019-05-21 16:50:45.114 +00:00",
      "episode": 8,
      "rating": 5,
      "animeId": 3087
    },
    {
      "id": 27827,
      "date": "2019-05-21 17:44:16.613 +00:00",
      "episode": 84,
      "rating": 5,
      "animeId": 1929
    },
    {
      "id": 27828,
      "date": "2019-05-21 18:01:37.147 +00:00",
      "episode": 7,
      "rating": 5,
      "animeId": 3122
    },
    {
      "id": 27829,
      "date": "2019-05-21 21:33:44.676 +00:00",
      "episode": 7,
      "rating": 6,
      "animeId": 3124
    },
    {
      "id": 27838,
      "date": "2019-05-22 15:49:26.058 +00:00",
      "episode": 7,
      "rating": 3,
      "animeId": 3126
    },
    {
      "id": 27839,
      "date": "2019-05-22 16:09:37.283 +00:00",
      "episode": 8,
      "rating": 5,
      "animeId": 3091
    },
    {
      "id": 27840,
      "date": "2019-05-22 16:21:03.310 +00:00",
      "episode": 7,
      "rating": 4,
      "animeId": 3125
    },
    {
      "id": 27843,
      "date": "2019-05-22 17:41:17.312 +00:00",
      "episode": 20,
      "rating": 6,
      "animeId": 3008
    },
    {
      "id": 27844,
      "date": "2019-05-22 18:03:11.905 +00:00",
      "episode": 7,
      "rating": 6,
      "animeId": 3127
    },
    {
      "id": 27845,
      "date": "2019-05-22 21:36:48.984 +00:00",
      "episode": 7,
      "rating": 5,
      "animeId": 3129
    },
    {
      "id": 27854,
      "date": "2019-05-23 15:42:04.543 +00:00",
      "episode": 15,
      "rating": 3,
      "animeId": 3040
    },
    {
      "id": 27859,
      "date": "2019-05-23 17:35:21.550 +00:00",
      "episode": 7,
      "rating": 5,
      "animeId": 3131
    },
    {
      "id": 27860,
      "date": "2019-05-23 17:58:52.259 +00:00",
      "episode": 30,
      "rating": 6,
      "animeId": 2821
    },
    {
      "id": 27861,
      "date": "2019-05-23 21:34:49.433 +00:00",
      "episode": 7,
      "rating": 6,
      "animeId": 3132
    },
    {
      "id": 27872,
      "date": "2019-05-24 16:36:43.210 +00:00",
      "episode": 7,
      "rating": 4,
      "animeId": 3133
    },
    {
      "id": 27873,
      "date": "2019-05-24 17:01:23.730 +00:00",
      "episode": 7,
      "rating": 6,
      "animeId": 3135
    },
    {
      "id": 27902,
      "date": "2019-05-25 15:50:19.002 +00:00",
      "episode": 8,
      "rating": 3,
      "animeId": 3107
    },
    {
      "id": 27903,
      "date": "2019-05-25 16:01:55.495 +00:00",
      "episode": 8,
      "rating": 4,
      "animeId": 3103
    },
    {
      "id": 27904,
      "date": "2019-05-25 16:23:10.780 +00:00",
      "episode": 8,
      "rating": 5,
      "animeId": 3102
    },
    {
      "id": 27905,
      "date": "2019-05-25 16:45:23.451 +00:00",
      "episode": 8,
      "rating": 6,
      "animeId": 3104
    },
    {
      "id": 27906,
      "date": "2019-05-25 16:48:31.930 +00:00",
      "episode": 3,
      "rating": 5,
      "animeId": 3212
    },
    {
      "id": 27907,
      "date": "2019-05-25 17:12:10.497 +00:00",
      "episode": 8,
      "rating": 6,
      "animeId": 3105
    },
    {
      "id": 27908,
      "date": "2019-05-25 20:00:05.966 +00:00",
      "episode": 31,
      "rating": 9,
      "animeId": 2652
    },
    {
      "id": 27937,
      "date": "2019-05-26 14:47:34.321 +00:00",
      "episode": 108,
      "rating": 4,
      "animeId": 122
    },
    {
      "id": 27938,
      "date": "2019-05-26 14:51:30.874 +00:00",
      "episode": 8,
      "rating": 5,
      "animeId": 3106
    },
    {
      "id": 27939,
      "date": "2019-05-26 14:58:26.637 +00:00",
      "episode": 8,
      "rating": 4,
      "animeId": 3110
    },
    {
      "id": 27940,
      "date": "2019-05-26 15:05:49.081 +00:00",
      "episode": 8,
      "rating": 4,
      "animeId": 3108
    },
    {
      "id": 27943,
      "date": "2019-05-26 16:05:02.475 +00:00",
      "episode": 8,
      "rating": 5,
      "animeId": 3112
    },
    {
      "id": 27944,
      "date": "2019-05-26 16:22:19.767 +00:00",
      "episode": 33,
      "rating": 5,
      "animeId": 2805
    },
    {
      "id": 27945,
      "date": "2019-05-26 16:41:13.603 +00:00",
      "episode": 8,
      "rating": 5,
      "animeId": 3109
    },
    {
      "id": 27946,
      "date": "2019-05-26 17:28:28.838 +00:00",
      "episode": 57,
      "rating": 5,
      "animeId": 2306
    },
    {
      "id": 27947,
      "date": "2019-05-26 17:52:33.879 +00:00",
      "episode": 8,
      "rating": 7,
      "animeId": 3111
    },
    {
      "id": 27948,
      "date": "2019-05-26 21:34:08.306 +00:00",
      "episode": 8,
      "rating": 6,
      "animeId": 3113
    },
    {
      "id": 27980,
      "date": "2019-05-27 15:00:50.967 +00:00",
      "episode": 8,
      "rating": 3,
      "animeId": 3117
    },
    {
      "id": 27981,
      "date": "2019-05-27 15:02:36.435 +00:00",
      "episode": 17,
      "rating": 3,
      "animeId": 2806
    },
    {
      "id": 27982,
      "date": "2019-05-27 15:05:38.654 +00:00",
      "episode": 8,
      "rating": 3,
      "animeId": 3123
    },
    {
      "id": 27984,
      "date": "2019-05-27 16:33:43.166 +00:00",
      "episode": 8,
      "rating": 3,
      "animeId": 3119
    },
    {
      "id": 27985,
      "date": "2019-05-27 16:45:13.652 +00:00",
      "episode": 3,
      "rating": 4,
      "animeId": 3216
    },
    {
      "id": 27986,
      "date": "2019-05-27 17:21:24.096 +00:00",
      "episode": 8,
      "rating": 5,
      "animeId": 3120
    },
    {
      "id": 27987,
      "date": "2019-05-27 17:42:14.350 +00:00",
      "episode": 8,
      "rating": 5,
      "animeId": 3118
    },
    {
      "id": 27988,
      "date": "2019-05-27 18:07:19.632 +00:00",
      "episode": 5,
      "rating": 9,
      "animeId": 3185
    },
    {
      "id": 27989,
      "date": "2019-05-27 21:38:22.963 +00:00",
      "episode": 20,
      "rating": 8,
      "animeId": 2986
    },
    {
      "id": 27997,
      "date": "2019-05-28 15:51:45.138 +00:00",
      "episode": 7,
      "rating": 3,
      "animeId": 3142
    },
    {
      "id": 27998,
      "date": "2019-05-28 16:09:14.029 +00:00",
      "episode": 8,
      "rating": 4,
      "animeId": 3121
    },
    {
      "id": 27999,
      "date": "2019-05-28 16:32:11.516 +00:00",
      "episode": 9,
      "rating": 4,
      "animeId": 3087
    },
    {
      "id": 28001,
      "date": "2019-05-28 17:06:33.861 +00:00",
      "episode": 85,
      "rating": 5,
      "animeId": 1929
    },
    {
      "id": 28002,
      "date": "2019-05-28 18:00:23.835 +00:00",
      "episode": 8,
      "rating": 4,
      "animeId": 3122
    },
    {
      "id": 28003,
      "date": "2019-05-28 21:35:31.847 +00:00",
      "episode": 8,
      "rating": 6,
      "animeId": 3124
    },
    {
      "id": 28011,
      "date": "2019-05-29 15:46:00.297 +00:00",
      "episode": 8,
      "rating": 3,
      "animeId": 3126
    },
    {
      "id": 28014,
      "date": "2019-05-29 16:35:01.765 +00:00",
      "episode": 9,
      "rating": 5,
      "animeId": 3091
    },
    {
      "id": 28015,
      "date": "2019-05-29 16:47:31.080 +00:00",
      "episode": 8,
      "rating": 5,
      "animeId": 3125
    },
    {
      "id": 28016,
      "date": "2019-05-29 17:46:54.485 +00:00",
      "episode": 21,
      "rating": 5,
      "animeId": 3008
    },
    {
      "id": 28017,
      "date": "2019-05-29 18:02:05.376 +00:00",
      "episode": 8,
      "rating": 5,
      "animeId": 3127
    },
    {
      "id": 28018,
      "date": "2019-05-29 21:33:58.116 +00:00",
      "episode": 8,
      "rating": 6,
      "animeId": 3129
    },
    {
      "id": 28028,
      "date": "2019-05-30 15:41:27.241 +00:00",
      "episode": 16,
      "rating": 3,
      "animeId": 3040
    },
    {
      "id": 28033,
      "date": "2019-05-30 17:40:09.185 +00:00",
      "episode": 8,
      "rating": 5,
      "animeId": 3131
    },
    {
      "id": 28034,
      "date": "2019-05-30 18:02:57.672 +00:00",
      "episode": 31,
      "rating": 5,
      "animeId": 2821
    },
    {
      "id": 28035,
      "date": "2019-05-30 21:40:25.112 +00:00",
      "episode": 8,
      "rating": 6,
      "animeId": 3132
    },
    {
      "id": 28044,
      "date": "2019-05-31 16:29:21.938 +00:00",
      "episode": 8,
      "rating": 4,
      "animeId": 3133
    },
    {
      "id": 28045,
      "date": "2019-05-31 16:51:55.046 +00:00",
      "episode": 8,
      "rating": 6,
      "animeId": 3135
    },
    {
      "id": 28075,
      "date": "2019-06-01 16:02:37.919 +00:00",
      "episode": 9,
      "rating": 4,
      "animeId": 3107
    },
    {
      "id": 28076,
      "date": "2019-06-01 16:13:59.752 +00:00",
      "episode": 9,
      "rating": 4,
      "animeId": 3103
    },
    {
      "id": 28077,
      "date": "2019-06-01 16:36:53.507 +00:00",
      "episode": 9,
      "rating": 5,
      "animeId": 3102
    },
    {
      "id": 28078,
      "date": "2019-06-01 16:59:08.830 +00:00",
      "episode": 9,
      "rating": 6,
      "animeId": 3105
    },
    {
      "id": 28079,
      "date": "2019-06-01 17:15:31.107 +00:00",
      "episode": 9,
      "rating": 6,
      "animeId": 3104
    },
    {
      "id": 28080,
      "date": "2019-06-01 20:04:32.318 +00:00",
      "episode": 32,
      "rating": 8,
      "animeId": 2652
    },
    {
      "id": 28100,
      "date": "2019-06-02 09:44:07.097 +00:00",
      "episode": 4,
      "rating": 4,
      "animeId": 3212
    },
    {
      "id": 28105,
      "date": "2019-06-02 14:44:27.133 +00:00",
      "episode": 109,
      "rating": 3,
      "animeId": 122
    },
    {
      "id": 28106,
      "date": "2019-06-02 14:46:57.006 +00:00",
      "episode": 9,
      "rating": 4,
      "animeId": 3106
    },
    {
      "id": 28107,
      "date": "2019-06-02 14:53:39.544 +00:00",
      "episode": 9,
      "rating": 4,
      "animeId": 3110
    },
    {
      "id": 28108,
      "date": "2019-06-02 15:01:28.698 +00:00",
      "episode": 9,
      "rating": 3,
      "animeId": 3108
    },
    {
      "id": 28109,
      "date": "2019-06-02 15:15:54.571 +00:00",
      "episode": 4,
      "rating": 4,
      "animeId": 3216
    },
    {
      "id": 28110,
      "date": "2019-06-02 15:34:47.554 +00:00",
      "episode": 9,
      "rating": 5,
      "animeId": 3112
    },
    {
      "id": 28111,
      "date": "2019-06-02 15:54:26.639 +00:00",
      "episode": 34,
      "rating": 5,
      "animeId": 2805
    },
    {
      "id": 28112,
      "date": "2019-06-02 16:17:21.136 +00:00",
      "episode": 9,
      "rating": 6,
      "animeId": 3109
    },
    {
      "id": 28113,
      "date": "2019-06-02 16:40:23.840 +00:00",
      "episode": 58,
      "rating": 4,
      "animeId": 2306
    },
    {
      "id": 28114,
      "date": "2019-06-02 17:03:35.400 +00:00",
      "episode": 9,
      "rating": 7,
      "animeId": 3111
    },
    {
      "id": 28115,
      "date": "2019-06-02 21:39:25.271 +00:00",
      "episode": 9,
      "rating": 7,
      "animeId": 3113
    },
    {
      "id": 28123,
      "date": "2019-06-03 15:40:07.064 +00:00",
      "episode": 9,
      "rating": 3,
      "animeId": 3123
    },
    {
      "id": 28126,
      "date": "2019-06-03 16:34:44.729 +00:00",
      "episode": 9,
      "rating": 4,
      "animeId": 3119
    },
    {
      "id": 28127,
      "date": "2019-06-03 16:46:31.402 +00:00",
      "episode": 9,
      "rating": 4,
      "animeId": 3120
    },
    {
      "id": 28128,
      "date": "2019-06-03 17:39:04.745 +00:00",
      "episode": 9,
      "rating": 4,
      "animeId": 3118
    },
    {
      "id": 28129,
      "date": "2019-06-03 18:01:57.539 +00:00",
      "episode": 6,
      "rating": 6,
      "animeId": 3185
    },
    {
      "id": 28130,
      "date": "2019-06-03 21:34:30.329 +00:00",
      "episode": 21,
      "rating": 7,
      "animeId": 2986
    },
    {
      "id": 28138,
      "date": "2019-06-04 15:59:33.514 +00:00",
      "episode": 8,
      "rating": 3,
      "animeId": 3142
    },
    {
      "id": 28139,
      "date": "2019-06-04 16:18:21.630 +00:00",
      "episode": 9,
      "rating": 3,
      "animeId": 3121
    },
    {
      "id": 28140,
      "date": "2019-06-04 16:39:15.825 +00:00",
      "episode": 10,
      "rating": 4,
      "animeId": 3087
    },
    {
      "id": 28141,
      "date": "2019-06-04 16:56:21.979 +00:00",
      "episode": 86,
      "rating": 5,
      "animeId": 1929
    },
    {
      "id": 28142,
      "date": "2019-06-04 17:43:02.411 +00:00",
      "episode": 9,
      "rating": 4,
      "animeId": 3122
    },
    {
      "id": 28153,
      "date": "2019-06-05 15:51:05.096 +00:00",
      "episode": 9,
      "rating": 2,
      "animeId": 3126
    },
    {
      "id": 28154,
      "date": "2019-06-05 16:08:50.466 +00:00",
      "episode": 10,
      "rating": 4,
      "animeId": 3091
    },
    {
      "id": 28155,
      "date": "2019-06-05 16:18:10.808 +00:00",
      "episode": 9,
      "rating": 4,
      "animeId": 3125
    },
    {
      "id": 28157,
      "date": "2019-06-05 16:47:24.847 +00:00",
      "episode": 22,
      "rating": 5,
      "animeId": 3008
    },
    {
      "id": 28159,
      "date": "2019-06-05 17:56:48.331 +00:00",
      "episode": 9,
      "rating": 5,
      "animeId": 3127
    },
    {
      "id": 28160,
      "date": "2019-06-05 21:37:25.424 +00:00",
      "episode": 9,
      "rating": 5,
      "animeId": 3129
    },
    {
      "id": 28169,
      "date": "2019-06-06 15:44:40.696 +00:00",
      "episode": 17,
      "rating": 3,
      "animeId": 3040
    },
    {
      "id": 28175,
      "date": "2019-06-06 17:38:48.317 +00:00",
      "episode": 9,
      "rating": 5,
      "animeId": 3131
    },
    {
      "id": 28176,
      "date": "2019-06-06 18:01:20.448 +00:00",
      "episode": 32,
      "rating": 5,
      "animeId": 2821
    },
    {
      "id": 28177,
      "date": "2019-06-06 21:35:21.244 +00:00",
      "episode": 9,
      "rating": 6,
      "animeId": 3132
    },
    {
      "id": 28188,
      "date": "2019-06-07 16:39:38.400 +00:00",
      "episode": 9,
      "rating": 4,
      "animeId": 3133
    },
    {
      "id": 28189,
      "date": "2019-06-07 17:02:27.244 +00:00",
      "episode": 9,
      "rating": 6,
      "animeId": 3135
    },
    {
      "id": 28219,
      "date": "2019-06-08 15:46:27.134 +00:00",
      "episode": 10,
      "rating": 3,
      "animeId": 3107
    },
    {
      "id": 28220,
      "date": "2019-06-08 15:59:54.614 +00:00",
      "episode": 10,
      "rating": 4,
      "animeId": 3103
    },
    {
      "id": 28221,
      "date": "2019-06-08 16:22:57.619 +00:00",
      "episode": 10,
      "rating": 5,
      "animeId": 3102
    },
    {
      "id": 28222,
      "date": "2019-06-08 16:37:48.645 +00:00",
      "episode": 10,
      "rating": 6,
      "animeId": 3104
    },
    {
      "id": 28223,
      "date": "2019-06-08 17:24:53.484 +00:00",
      "episode": 10,
      "rating": 7,
      "animeId": 3105
    },
    {
      "id": 28225,
      "date": "2019-06-08 19:47:40.575 +00:00",
      "episode": 5,
      "rating": 6,
      "animeId": 3212
    },
    {
      "id": 28226,
      "date": "2019-06-08 20:10:52.116 +00:00",
      "episode": 33,
      "rating": 9,
      "animeId": 2652
    },
    {
      "id": 28251,
      "date": "2019-06-09 14:41:43.698 +00:00",
      "episode": 110,
      "rating": 3,
      "animeId": 122
    },
    {
      "id": 28252,
      "date": "2019-06-09 14:46:13.868 +00:00",
      "episode": 10,
      "rating": 4,
      "animeId": 3106
    },
    {
      "id": 28253,
      "date": "2019-06-09 14:52:06.221 +00:00",
      "episode": 10,
      "rating": 4,
      "animeId": 3110
    },
    {
      "id": 28254,
      "date": "2019-06-09 15:04:35.214 +00:00",
      "episode": 10,
      "rating": 3,
      "animeId": 3108
    },
    {
      "id": 28256,
      "date": "2019-06-09 15:34:26.841 +00:00",
      "episode": 5,
      "rating": 3,
      "animeId": 3216
    },
    {
      "id": 28257,
      "date": "2019-06-09 15:59:44.998 +00:00",
      "episode": 10,
      "rating": 5,
      "animeId": 3112
    },
    {
      "id": 28258,
      "date": "2019-06-09 16:22:02.517 +00:00",
      "episode": 35,
      "rating": 5,
      "animeId": 2805
    },
    {
      "id": 28259,
      "date": "2019-06-09 16:42:24.933 +00:00",
      "episode": 59,
      "rating": 4,
      "animeId": 2306
    },
    {
      "id": 28260,
      "date": "2019-06-09 17:39:17.546 +00:00",
      "episode": 10,
      "rating": 6,
      "animeId": 3109
    },
    {
      "id": 28261,
      "date": "2019-06-09 18:03:42.540 +00:00",
      "episode": 10,
      "rating": 7,
      "animeId": 3111
    },
    {
      "id": 28262,
      "date": "2019-06-09 21:36:03.964 +00:00",
      "episode": 10,
      "rating": 6,
      "animeId": 3113
    },
    {
      "id": 28270,
      "date": "2019-06-10 15:56:59.071 +00:00",
      "episode": 10,
      "rating": 3,
      "animeId": 3119
    },
    {
      "id": 28271,
      "date": "2019-06-10 16:01:41.420 +00:00",
      "episode": 10,
      "rating": 4,
      "animeId": 3123
    },
    {
      "id": 28272,
      "date": "2019-06-10 16:18:44.097 +00:00",
      "episode": 8,
      "rating": 5,
      "animeId": 3116
    },
    {
      "id": 28274,
      "date": "2019-06-10 16:46:04.522 +00:00",
      "episode": 10,
      "rating": 5,
      "animeId": 3120
    },
    {
      "id": 28275,
      "date": "2019-06-10 17:35:44.524 +00:00",
      "episode": 10,
      "rating": 5,
      "animeId": 3118
    },
    {
      "id": 28276,
      "date": "2019-06-10 18:00:01.063 +00:00",
      "episode": 7,
      "rating": 6,
      "animeId": 3185
    },
    {
      "id": 28277,
      "date": "2019-06-10 21:40:46.501 +00:00",
      "episode": 22,
      "rating": 7,
      "animeId": 2986
    },
    {
      "id": 28285,
      "date": "2019-06-11 15:53:22.142 +00:00",
      "episode": 9,
      "rating": 4,
      "animeId": 3142
    },
    {
      "id": 28286,
      "date": "2019-06-11 16:08:53.957 +00:00",
      "episode": 10,
      "rating": 4,
      "animeId": 3121
    },
    {
      "id": 28288,
      "date": "2019-06-11 16:40:24.418 +00:00",
      "episode": 11,
      "rating": 4,
      "animeId": 3087
    },
    {
      "id": 28289,
      "date": "2019-06-11 16:57:52.216 +00:00",
      "episode": 87,
      "rating": 4,
      "animeId": 1929
    },
    {
      "id": 28290,
      "date": "2019-06-11 17:43:36.804 +00:00",
      "episode": 10,
      "rating": 4,
      "animeId": 3122
    },
    {
      "id": 28294,
      "date": "2019-06-11 21:42:43.856 +00:00",
      "episode": 9,
      "rating": 6,
      "animeId": 3124
    },
    {
      "id": 28302,
      "date": "2019-06-12 15:50:13.531 +00:00",
      "episode": 10,
      "rating": 3,
      "animeId": 3126
    },
    {
      "id": 28303,
      "date": "2019-06-12 16:08:04.937 +00:00",
      "episode": 11,
      "rating": 5,
      "animeId": 3091
    },
    {
      "id": 28304,
      "date": "2019-06-12 16:18:03.677 +00:00",
      "episode": 10,
      "rating": 4,
      "animeId": 3125
    },
    {
      "id": 28306,
      "date": "2019-06-12 16:52:43.670 +00:00",
      "episode": 23,
      "rating": 5,
      "animeId": 3008
    },
    {
      "id": 28307,
      "date": "2019-06-12 17:38:02.975 +00:00",
      "episode": 10,
      "rating": 5,
      "animeId": 3127
    },
    {
      "id": 28309,
      "date": "2019-06-12 21:38:56.052 +00:00",
      "episode": 10,
      "rating": 6,
      "animeId": 3129
    },
    {
      "id": 28317,
      "date": "2019-06-13 15:43:13.908 +00:00",
      "episode": 18,
      "rating": 3,
      "animeId": 3040
    },
    {
      "id": 28323,
      "date": "2019-06-13 17:06:49.022 +00:00",
      "episode": 10,
      "rating": 5,
      "animeId": 3131
    },
    {
      "id": 28324,
      "date": "2019-06-13 17:50:34.849 +00:00",
      "episode": 33,
      "rating": 5,
      "animeId": 2821
    },
    {
      "id": 28325,
      "date": "2019-06-13 21:33:27.626 +00:00",
      "episode": 10,
      "rating": 5,
      "animeId": 3132
    },
    {
      "id": 28334,
      "date": "2019-06-14 16:36:56.302 +00:00",
      "episode": 10,
      "rating": 4,
      "animeId": 3133
    },
    {
      "id": 28335,
      "date": "2019-06-14 17:00:24.451 +00:00",
      "episode": 10,
      "rating": 5,
      "animeId": 3135
    },
    {
      "id": 28364,
      "date": "2019-06-15 15:41:44.927 +00:00",
      "episode": 11,
      "rating": 3,
      "animeId": 3107
    },
    {
      "id": 28366,
      "date": "2019-06-15 16:08:51.134 +00:00",
      "episode": 11,
      "rating": 6,
      "animeId": 3103
    },
    {
      "id": 28367,
      "date": "2019-06-15 16:31:32.526 +00:00",
      "episode": 11,
      "rating": 5,
      "animeId": 3102
    },
    {
      "id": 28368,
      "date": "2019-06-15 16:43:04.982 +00:00",
      "episode": 11,
      "rating": 7,
      "animeId": 3104
    },
    {
      "id": 28369,
      "date": "2019-06-15 17:39:01.517 +00:00",
      "episode": 11,
      "rating": 7,
      "animeId": 3105
    },
    {
      "id": 28370,
      "date": "2019-06-15 19:38:16.539 +00:00",
      "episode": 6,
      "rating": 5,
      "animeId": 3212
    },
    {
      "id": 28371,
      "date": "2019-06-15 20:03:52.209 +00:00",
      "episode": 34,
      "rating": 8,
      "animeId": 2652
    },
    {
      "id": 28394,
      "date": "2019-06-16 14:36:24.478 +00:00",
      "episode": 111,
      "rating": 3,
      "animeId": 122
    },
    {
      "id": 28395,
      "date": "2019-06-16 14:50:20.101 +00:00",
      "episode": 6,
      "rating": 3,
      "animeId": 3216
    },
    {
      "id": 28397,
      "date": "2019-06-16 15:06:46.017 +00:00",
      "episode": 11,
      "rating": 3,
      "animeId": 3106
    },
    {
      "id": 28398,
      "date": "2019-06-16 15:16:51.098 +00:00",
      "episode": 11,
      "rating": 4,
      "animeId": 3108
    },
    {
      "id": 28399,
      "date": "2019-06-16 15:24:20.734 +00:00",
      "episode": 11,
      "rating": 4,
      "animeId": 3110
    },
    {
      "id": 28400,
      "date": "2019-06-16 15:46:05.610 +00:00",
      "episode": 11,
      "rating": 5,
      "animeId": 3112
    },
    {
      "id": 28401,
      "date": "2019-06-16 16:08:34.471 +00:00",
      "episode": 36,
      "rating": 5,
      "animeId": 2805
    },
    {
      "id": 28402,
      "date": "2019-06-16 16:37:44.681 +00:00",
      "episode": 60,
      "rating": 4,
      "animeId": 2306
    },
    {
      "id": 28403,
      "date": "2019-06-16 17:00:45.147 +00:00",
      "episode": 11,
      "rating": 5,
      "animeId": 3109
    },
    {
      "id": 28404,
      "date": "2019-06-16 17:23:20.805 +00:00",
      "episode": 11,
      "rating": 7,
      "animeId": 3111
    },
    {
      "id": 28405,
      "date": "2019-06-16 21:36:37.369 +00:00",
      "episode": 11,
      "rating": 6,
      "animeId": 3113
    },
    {
      "id": 28413,
      "date": "2019-06-17 15:41:24.002 +00:00",
      "episode": 11,
      "rating": 3,
      "animeId": 3123
    },
    {
      "id": 28414,
      "date": "2019-06-17 15:58:31.489 +00:00",
      "episode": 11,
      "rating": 3,
      "animeId": 3119
    },
    {
      "id": 28416,
      "date": "2019-06-17 16:36:42.724 +00:00",
      "episode": 9,
      "rating": 5,
      "animeId": 3116
    },
    {
      "id": 28417,
      "date": "2019-06-17 16:48:16.978 +00:00",
      "episode": 11,
      "rating": 4,
      "animeId": 3120
    },
    {
      "id": 28418,
      "date": "2019-06-17 17:42:01.931 +00:00",
      "episode": 11,
      "rating": 5,
      "animeId": 3118
    },
    {
      "id": 28419,
      "date": "2019-06-17 18:05:04.183 +00:00",
      "episode": 8,
      "rating": 7,
      "animeId": 3185
    },
    {
      "id": 28420,
      "date": "2019-06-17 21:44:22.733 +00:00",
      "episode": 23,
      "rating": 7,
      "animeId": 2986
    },
    {
      "id": 28429,
      "date": "2019-06-18 16:10:04.824 +00:00",
      "episode": 10,
      "rating": 3,
      "animeId": 3142
    },
    {
      "id": 28430,
      "date": "2019-06-18 16:16:07.167 +00:00",
      "episode": 11,
      "rating": 4,
      "animeId": 3121
    },
    {
      "id": 28432,
      "date": "2019-06-18 16:50:26.857 +00:00",
      "episode": 12,
      "rating": 4,
      "animeId": 3087
    },
    {
      "id": 28433,
      "date": "2019-06-18 17:10:28.113 +00:00",
      "episode": 11,
      "rating": 4,
      "animeId": 3122
    },
    {
      "id": 28434,
      "date": "2019-06-18 18:08:37.026 +00:00",
      "episode": 88,
      "rating": 4,
      "animeId": 1929
    },
    {
      "id": 28435,
      "date": "2019-06-18 21:44:54.854 +00:00",
      "episode": 10,
      "rating": 7,
      "animeId": 3124
    },
    {
      "id": 28443,
      "date": "2019-06-19 15:48:07.730 +00:00",
      "episode": 11,
      "rating": 2,
      "animeId": 3126
    },
    {
      "id": 28444,
      "date": "2019-06-19 16:09:57.987 +00:00",
      "episode": 12,
      "rating": 5,
      "animeId": 3091
    },
    {
      "id": 28445,
      "date": "2019-06-19 16:21:05.074 +00:00",
      "episode": 11,
      "rating": 3,
      "animeId": 3125
    },
    {
      "id": 28448,
      "date": "2019-06-19 17:39:02.550 +00:00",
      "episode": 24,
      "rating": 5,
      "animeId": 3008
    },
    {
      "id": 28449,
      "date": "2019-06-19 18:00:48.699 +00:00",
      "episode": 11,
      "rating": 5,
      "animeId": 3127
    },
    {
      "id": 28450,
      "date": "2019-06-19 21:37:39.014 +00:00",
      "episode": 11,
      "rating": 6,
      "animeId": 3129
    },
    {
      "id": 28458,
      "date": "2019-06-20 15:19:53.303 +00:00",
      "episode": 19,
      "rating": 3,
      "animeId": 3040
    },
    {
      "id": 28464,
      "date": "2019-06-20 17:27:58.871 +00:00",
      "episode": 11,
      "rating": 5,
      "animeId": 3131
    },
    {
      "id": 28465,
      "date": "2019-06-20 17:49:53.690 +00:00",
      "episode": 34,
      "rating": 5,
      "animeId": 2821
    },
    {
      "id": 28466,
      "date": "2019-06-20 21:32:32.214 +00:00",
      "episode": 11,
      "rating": 6,
      "animeId": 3132
    },
    {
      "id": 28482,
      "date": "2019-06-21 16:37:47.044 +00:00",
      "episode": 11,
      "rating": 4,
      "animeId": 3133
    },
    {
      "id": 28483,
      "date": "2019-06-21 16:59:05.530 +00:00",
      "episode": 11,
      "rating": 5,
      "animeId": 3135
    },
    {
      "id": 28510,
      "date": "2019-06-22 14:20:55.510 +00:00",
      "episode": 12,
      "rating": 3,
      "animeId": 2515
    },
    {
      "id": 28517,
      "date": "2019-06-22 15:57:09.045 +00:00",
      "episode": 12,
      "rating": 3,
      "animeId": 3107
    },
    {
      "id": 28518,
      "date": "2019-06-22 16:07:24.334 +00:00",
      "episode": 12,
      "rating": 4,
      "animeId": 3103
    },
    {
      "id": 28519,
      "date": "2019-06-22 16:28:52.784 +00:00",
      "episode": 12,
      "rating": 5,
      "animeId": 3102
    },
    {
      "id": 28520,
      "date": "2019-06-22 16:41:02.688 +00:00",
      "episode": 12,
      "rating": 6,
      "animeId": 3104
    },
    {
      "id": 28521,
      "date": "2019-06-22 17:42:20.431 +00:00",
      "episode": 12,
      "rating": 7,
      "animeId": 3105
    },
    {
      "id": 28522,
      "date": "2019-06-22 17:51:36.707 +00:00",
      "episode": 7,
      "rating": 7,
      "animeId": 3212
    },
    {
      "id": 28523,
      "date": "2019-06-22 19:53:45.660 +00:00",
      "episode": 35,
      "rating": 8,
      "animeId": 2652
    },
    {
      "id": 28551,
      "date": "2019-06-23 14:43:11.873 +00:00",
      "episode": 112,
      "rating": 2,
      "animeId": 122
    },
    {
      "id": 28552,
      "date": "2019-06-23 14:56:58.779 +00:00",
      "episode": 7,
      "rating": 4,
      "animeId": 3216
    },
    {
      "id": 28556,
      "date": "2019-06-23 15:40:49.372 +00:00",
      "episode": 12,
      "rating": 3,
      "animeId": 3106
    },
    {
      "id": 28557,
      "date": "2019-06-23 15:49:26.636 +00:00",
      "episode": 12,
      "rating": 4,
      "animeId": 3108
    },
    {
      "id": 28558,
      "date": "2019-06-23 15:55:14.573 +00:00",
      "episode": 12,
      "rating": 4,
      "animeId": 3110
    },
    {
      "id": 28559,
      "date": "2019-06-23 16:18:03.251 +00:00",
      "episode": 12,
      "rating": 5,
      "animeId": 3112
    },
    {
      "id": 28560,
      "date": "2019-06-23 16:34:42.367 +00:00",
      "episode": 37,
      "rating": 5,
      "animeId": 2805
    },
    {
      "id": 28561,
      "date": "2019-06-23 17:29:29.627 +00:00",
      "episode": 61,
      "rating": 6,
      "animeId": 2306
    },
    {
      "id": 28562,
      "date": "2019-06-23 17:44:58.440 +00:00",
      "episode": 12,
      "rating": 6,
      "animeId": 3109
    },
    {
      "id": 28563,
      "date": "2019-06-23 18:06:48.852 +00:00",
      "episode": 12,
      "rating": 7,
      "animeId": 3111
    },
    {
      "id": 28564,
      "date": "2019-06-23 21:39:09.347 +00:00",
      "episode": 12,
      "rating": 6,
      "animeId": 3113
    },
    {
      "id": 28573,
      "date": "2019-06-24 15:20:39.933 +00:00",
      "episode": 12,
      "rating": 3,
      "animeId": 3123
    },
    {
      "id": 28574,
      "date": "2019-06-24 15:53:04.582 +00:00",
      "episode": 12,
      "rating": 3,
      "animeId": 3119
    },
    {
      "id": 28577,
      "date": "2019-06-24 16:29:59.677 +00:00",
      "episode": 10,
      "rating": 4,
      "animeId": 3116
    },
    {
      "id": 28578,
      "date": "2019-06-24 16:40:07.842 +00:00",
      "episode": 12,
      "rating": 5,
      "animeId": 3120
    },
    {
      "id": 28579,
      "date": "2019-06-24 17:42:28.319 +00:00",
      "episode": 12,
      "rating": 5,
      "animeId": 3118
    },
    {
      "id": 28580,
      "date": "2019-06-24 18:09:34.703 +00:00",
      "episode": 9,
      "rating": 6,
      "animeId": 3185
    },
    {
      "id": 28581,
      "date": "2019-06-24 21:38:27.539 +00:00",
      "episode": 24,
      "rating": 8,
      "animeId": 2986
    },
    {
      "id": 28590,
      "date": "2019-06-25 15:50:34.509 +00:00",
      "episode": 11,
      "rating": 3,
      "animeId": 3142
    },
    {
      "id": 28591,
      "date": "2019-06-25 16:11:03.005 +00:00",
      "episode": 12,
      "rating": 2,
      "animeId": 3121
    },
    {
      "id": 28592,
      "date": "2019-06-25 16:32:17.239 +00:00",
      "episode": 13,
      "rating": 4,
      "animeId": 3087
    },
    {
      "id": 28593,
      "date": "2019-06-25 16:52:48.096 +00:00",
      "episode": 12,
      "rating": 4,
      "animeId": 3122
    },
    {
      "id": 28595,
      "date": "2019-06-25 17:57:19.926 +00:00",
      "episode": 89,
      "rating": 4,
      "animeId": 1929
    },
    {
      "id": 28596,
      "date": "2019-06-25 21:36:56.530 +00:00",
      "episode": 11,
      "rating": 7,
      "animeId": 3124
    },
    {
      "id": 28604,
      "date": "2019-06-26 15:49:31.942 +00:00",
      "episode": 12,
      "rating": 2,
      "animeId": 3126
    },
    {
      "id": 28605,
      "date": "2019-06-26 16:09:09.939 +00:00",
      "episode": 13,
      "rating": 5,
      "animeId": 3091
    },
    {
      "id": 28606,
      "date": "2019-06-26 16:18:45.662 +00:00",
      "episode": 12,
      "rating": 4,
      "animeId": 3125
    },
    {
      "id": 28608,
      "date": "2019-06-26 17:32:56.107 +00:00",
      "episode": 25,
      "rating": 5,
      "animeId": 3008
    },
    {
      "id": 28609,
      "date": "2019-06-26 18:01:28.351 +00:00",
      "episode": 12,
      "rating": 6,
      "animeId": 3127
    },
    {
      "id": 28610,
      "date": "2019-06-26 21:38:18.149 +00:00",
      "episode": 12,
      "rating": 5,
      "animeId": 3129
    },
    {
      "id": 28624,
      "date": "2019-06-27 16:52:47.935 +00:00",
      "episode": 12,
      "rating": 5,
      "animeId": 3131
    },
    {
      "id": 28625,
      "date": "2019-06-27 17:09:30.018 +00:00",
      "episode": 35,
      "rating": 5,
      "animeId": 2821
    },
    {
      "id": 28626,
      "date": "2019-06-27 17:59:13.064 +00:00",
      "episode": 36,
      "rating": 5,
      "animeId": 2821
    },
    {
      "id": 28627,
      "date": "2019-06-27 21:36:39.307 +00:00",
      "episode": 12,
      "rating": 5,
      "animeId": 3132
    },
    {
      "id": 28636,
      "date": "2019-06-28 15:39:46.887 +00:00",
      "episode": 20,
      "rating": 3,
      "animeId": 3040
    },
    {
      "id": 28640,
      "date": "2019-06-28 16:51:19.028 +00:00",
      "episode": 12,
      "rating": 6,
      "animeId": 3135
    },
    {
      "id": 28677,
      "date": "2019-06-29 15:58:55.051 +00:00",
      "episode": 13,
      "rating": 4,
      "animeId": 3107
    },
    {
      "id": 28678,
      "date": "2019-06-29 16:15:27.093 +00:00",
      "episode": 13,
      "rating": 6,
      "animeId": 3102
    },
    {
      "id": 28681,
      "date": "2019-06-29 17:07:03.671 +00:00",
      "episode": 8,
      "rating": 5,
      "animeId": 3212
    },
    {
      "id": 28682,
      "date": "2019-06-29 20:04:22.434 +00:00",
      "episode": 36,
      "rating": 9,
      "animeId": 2652
    },
    {
      "id": 28712,
      "date": "2019-06-30 14:38:11.248 +00:00",
      "episode": 113,
      "rating": 3,
      "animeId": 122
    },
    {
      "id": 28713,
      "date": "2019-06-30 14:50:59.990 +00:00",
      "episode": 8,
      "rating": 4,
      "animeId": 3216
    },
    {
      "id": 28719,
      "date": "2019-06-30 15:59:01.719 +00:00",
      "episode": 13,
      "rating": 6,
      "animeId": 3112
    },
    {
      "id": 28720,
      "date": "2019-06-30 16:16:11.603 +00:00",
      "episode": 38,
      "rating": 5,
      "animeId": 2805
    },
    {
      "id": 28721,
      "date": "2019-06-30 16:37:36.672 +00:00",
      "episode": 62,
      "rating": 6,
      "animeId": 2306
    },
    {
      "id": 28722,
      "date": "2019-06-30 16:59:35.332 +00:00",
      "episode": 13,
      "rating": 5,
      "animeId": 3109
    },
    {
      "id": 28723,
      "date": "2019-06-30 21:34:56.917 +00:00",
      "episode": 13,
      "rating": 6,
      "animeId": 3111
    }
  ]
}
